{
"meta":{"test_sets":[],"test_metrics":[],"learn_metrics":[{"best_value":"Min","name":"Logloss"}],"launch_mode":"Train","parameters":"","iteration_count":1000,"learn_sets":["learn"],"name":"experiment"},
"iterations":[
{"learn":[0.6639393767],"iteration":0,"passed_time":0.3232596771,"remaining_time":322.9364174},
{"learn":[0.6388240567],"iteration":1,"passed_time":0.3565096055,"remaining_time":177.8982931},
{"learn":[0.6132712181],"iteration":2,"passed_time":0.4057863453,"remaining_time":134.8563288},
{"learn":[0.5916788744],"iteration":3,"passed_time":0.5243446665,"remaining_time":130.561822},
{"learn":[0.5713599333],"iteration":4,"passed_time":0.6235729728,"remaining_time":124.0910216},
{"learn":[0.5521114995],"iteration":5,"passed_time":0.6605982316,"remaining_time":109.439107},
{"learn":[0.5338419888],"iteration":6,"passed_time":0.6982701227,"remaining_time":99.05460454},
{"learn":[0.5173159352],"iteration":7,"passed_time":0.7299929626,"remaining_time":90.51912736},
{"learn":[0.5026565662],"iteration":8,"passed_time":0.7634074284,"remaining_time":84.05964017},
{"learn":[0.4886830964],"iteration":9,"passed_time":0.8045075839,"remaining_time":79.64625081},
{"learn":[0.4762177453],"iteration":10,"passed_time":0.836130413,"remaining_time":75.17572531},
{"learn":[0.464443829],"iteration":11,"passed_time":0.893951366,"remaining_time":73.6019958},
{"learn":[0.4545361517],"iteration":12,"passed_time":0.9272699887,"remaining_time":70.40119068},
{"learn":[0.4448371887],"iteration":13,"passed_time":0.9589193265,"remaining_time":67.53531828},
{"learn":[0.437207952],"iteration":14,"passed_time":0.9959976017,"remaining_time":65.40384251},
{"learn":[0.4303552371],"iteration":15,"passed_time":1.029877734,"remaining_time":63.33748063},
{"learn":[0.4226497129],"iteration":16,"passed_time":1.06148152,"remaining_time":61.3786079},
{"learn":[0.4152639144],"iteration":17,"passed_time":1.138542979,"remaining_time":62.11384475},
{"learn":[0.4084680154],"iteration":18,"passed_time":1.17371772,"remaining_time":60.60089915},
{"learn":[0.4021904163],"iteration":19,"passed_time":1.206841608,"remaining_time":59.13523881},
{"learn":[0.3965376731],"iteration":20,"passed_time":1.238335217,"remaining_time":57.73000843},
{"learn":[0.3912344409],"iteration":21,"passed_time":1.274230304,"remaining_time":56.64532895},
{"learn":[0.3861204725],"iteration":22,"passed_time":1.309991161,"remaining_time":55.64614625},
{"learn":[0.3821605454],"iteration":23,"passed_time":1.356419782,"remaining_time":55.16107112},
{"learn":[0.3776558225],"iteration":24,"passed_time":1.392167526,"remaining_time":54.29453353},
{"learn":[0.3735522662],"iteration":25,"passed_time":1.422226193,"remaining_time":53.27878123},
{"learn":[0.3697142007],"iteration":26,"passed_time":1.453365764,"remaining_time":52.37499585},
{"learn":[0.3659679027],"iteration":27,"passed_time":1.494779988,"remaining_time":51.89021957},
{"learn":[0.3625397105],"iteration":28,"passed_time":1.526777543,"remaining_time":51.12072395},
{"learn":[0.3590701074],"iteration":29,"passed_time":1.559749003,"remaining_time":50.43188442},
{"learn":[0.3561102878],"iteration":30,"passed_time":1.595135969,"remaining_time":49.86086303},
{"learn":[0.3539820844],"iteration":31,"passed_time":1.626739042,"remaining_time":49.20885603},
{"learn":[0.3508340861],"iteration":32,"passed_time":1.659999161,"remaining_time":48.64300571},
{"learn":[0.3481219817],"iteration":33,"passed_time":1.694653484,"remaining_time":48.14809606},
{"learn":[0.3455351333],"iteration":34,"passed_time":1.725933212,"remaining_time":47.58644426},
{"learn":[0.3433775131],"iteration":35,"passed_time":1.773715351,"remaining_time":47.49615551},
{"learn":[0.3411288192],"iteration":36,"passed_time":1.809173721,"remaining_time":47.08741334},
{"learn":[0.3392779272],"iteration":37,"passed_time":1.839896538,"remaining_time":46.5784334},
{"learn":[0.337516644],"iteration":38,"passed_time":1.91542964,"remaining_time":47.19815088},
{"learn":[0.3352097926],"iteration":39,"passed_time":1.946953934,"remaining_time":46.72689443},
{"learn":[0.333879794],"iteration":40,"passed_time":1.97813436,"remaining_time":46.26904515},
{"learn":[0.3320180789],"iteration":41,"passed_time":2.019819567,"remaining_time":46.0711225},
{"learn":[0.3307692986],"iteration":42,"passed_time":2.059684176,"remaining_time":45.83994782},
{"learn":[0.3290101703],"iteration":43,"passed_time":2.093520305,"remaining_time":45.48648662},
{"learn":[0.3279829314],"iteration":44,"passed_time":2.137566543,"remaining_time":45.36391219},
{"learn":[0.3268008902],"iteration":45,"passed_time":2.190537437,"remaining_time":45.42984163},
{"learn":[0.3257056385],"iteration":46,"passed_time":2.222444545,"remaining_time":45.0636096},
{"learn":[0.3243959088],"iteration":47,"passed_time":2.253841632,"remaining_time":44.70119236},
{"learn":[0.3231558427],"iteration":48,"passed_time":2.288111593,"remaining_time":44.40804337},
{"learn":[0.3220995978],"iteration":49,"passed_time":2.32152405,"remaining_time":44.10895695},
{"learn":[0.3211131229],"iteration":50,"passed_time":2.353826685,"remaining_time":43.79963773},
{"learn":[0.3195788876],"iteration":51,"passed_time":2.391715843,"remaining_time":43.6028196},
{"learn":[0.3184333974],"iteration":52,"passed_time":2.455684827,"remaining_time":43.87799115},
{"learn":[0.3173568996],"iteration":53,"passed_time":2.503065014,"remaining_time":43.84999081},
{"learn":[0.3161114702],"iteration":54,"passed_time":2.540606116,"remaining_time":43.65223235},
{"learn":[0.3153325356],"iteration":55,"passed_time":2.603215452,"remaining_time":43.88277476},
{"learn":[0.3144104387],"iteration":56,"passed_time":2.646233636,"remaining_time":43.77891787},
{"learn":[0.3132536487],"iteration":57,"passed_time":2.701494777,"remaining_time":43.87600138},
{"learn":[0.3127208808],"iteration":58,"passed_time":2.742438679,"remaining_time":43.73957284},
{"learn":[0.3119535099],"iteration":59,"passed_time":2.781152969,"remaining_time":43.57139652},
{"learn":[0.3111082454],"iteration":60,"passed_time":2.819339742,"remaining_time":43.39934455},
{"learn":[0.3103994448],"iteration":61,"passed_time":2.867153161,"remaining_time":43.37725266},
{"learn":[0.3098412002],"iteration":62,"passed_time":2.908421667,"remaining_time":43.25700162},
{"learn":[0.3091524032],"iteration":63,"passed_time":2.949627685,"remaining_time":43.13830489},
{"learn":[0.3084238507],"iteration":64,"passed_time":3.000116813,"remaining_time":43.15552647},
{"learn":[0.3077504731],"iteration":65,"passed_time":3.031261099,"remaining_time":42.89693738},
{"learn":[0.3071833523],"iteration":66,"passed_time":3.070037927,"remaining_time":42.75142367},
{"learn":[0.3064495762],"iteration":67,"passed_time":3.102865019,"remaining_time":42.5275029},
{"learn":[0.3055552752],"iteration":68,"passed_time":3.137435243,"remaining_time":42.33264074},
{"learn":[0.3046419854],"iteration":69,"passed_time":3.169662574,"remaining_time":42.11123134},
{"learn":[0.3037851082],"iteration":70,"passed_time":3.20245987,"remaining_time":41.90260872},
{"learn":[0.3032771446],"iteration":71,"passed_time":3.232957966,"remaining_time":41.66923601},
{"learn":[0.3023473047],"iteration":72,"passed_time":3.264074299,"remaining_time":41.44927226},
{"learn":[0.301786412],"iteration":73,"passed_time":3.298985153,"remaining_time":41.28189529},
{"learn":[0.301277708],"iteration":74,"passed_time":3.32972946,"remaining_time":41.06666334},
{"learn":[0.3007546962],"iteration":75,"passed_time":3.364943404,"remaining_time":40.9106277},
{"learn":[0.3001497518],"iteration":76,"passed_time":3.415984393,"remaining_time":40.94744928},
{"learn":[0.2994079617],"iteration":77,"passed_time":3.448759157,"remaining_time":40.76610183},
{"learn":[0.2987377471],"iteration":78,"passed_time":3.489981336,"remaining_time":40.68699761},
{"learn":[0.2982724967],"iteration":79,"passed_time":3.620696045,"remaining_time":41.63800451},
{"learn":[0.2978629399],"iteration":80,"passed_time":3.713852978,"remaining_time":42.13618379},
{"learn":[0.2973716263],"iteration":81,"passed_time":3.768739545,"remaining_time":42.1914988},
{"learn":[0.2965599159],"iteration":82,"passed_time":3.844864676,"remaining_time":42.47880611},
{"learn":[0.2961178755],"iteration":83,"passed_time":3.903744472,"remaining_time":42.569404},
{"learn":[0.2956622101],"iteration":84,"passed_time":3.934683366,"remaining_time":42.35570917},
{"learn":[0.2950775219],"iteration":85,"passed_time":3.971910347,"remaining_time":42.21309369},
{"learn":[0.2946021911],"iteration":86,"passed_time":4.00977517,"remaining_time":42.0795946},
{"learn":[0.2942395648],"iteration":87,"passed_time":4.041444069,"remaining_time":41.88405672},
{"learn":[0.2938082492],"iteration":88,"passed_time":4.082121514,"remaining_time":41.78441235},
{"learn":[0.2931077101],"iteration":89,"passed_time":4.11411995,"remaining_time":41.59832393},
{"learn":[0.2926025991],"iteration":90,"passed_time":4.145145593,"remaining_time":41.40590488},
{"learn":[0.2920822226],"iteration":91,"passed_time":4.179926598,"remaining_time":41.25405816},
{"learn":[0.2915520163],"iteration":92,"passed_time":4.214229479,"remaining_time":41.100066},
{"learn":[0.2909317974],"iteration":93,"passed_time":4.260867589,"remaining_time":41.06751102},
{"learn":[0.2903803407],"iteration":94,"passed_time":4.296372396,"remaining_time":40.9286002},
{"learn":[0.2900541202],"iteration":95,"passed_time":4.326840617,"remaining_time":40.74441581},
{"learn":[0.2895846503],"iteration":96,"passed_time":4.357741589,"remaining_time":40.56742943},
{"learn":[0.288894121],"iteration":97,"passed_time":4.396876338,"remaining_time":40.46920874},
{"learn":[0.2885535813],"iteration":98,"passed_time":4.428422332,"remaining_time":40.30311638},
{"learn":[0.288163296],"iteration":99,"passed_time":4.461294732,"remaining_time":40.15165259},
{"learn":[0.2876912292],"iteration":100,"passed_time":4.49812374,"remaining_time":40.03775488},
{"learn":[0.2874449461],"iteration":101,"passed_time":4.52750036,"remaining_time":39.85975807},
{"learn":[0.2869046303],"iteration":102,"passed_time":4.559060431,"remaining_time":39.7036622},
{"learn":[0.2865767778],"iteration":103,"passed_time":4.593208364,"remaining_time":39.57225668},
{"learn":[0.2861187402],"iteration":104,"passed_time":4.639325894,"remaining_time":39.54473024},
{"learn":[0.2855143972],"iteration":105,"passed_time":4.675522998,"remaining_time":39.43318453},
{"learn":[0.2849223912],"iteration":106,"passed_time":4.708574184,"remaining_time":39.29679202},
{"learn":[0.2846164282],"iteration":107,"passed_time":4.73856329,"remaining_time":39.13702273},
{"learn":[0.2843753258],"iteration":108,"passed_time":4.768121983,"remaining_time":38.97611639},
{"learn":[0.2839373204],"iteration":109,"passed_time":4.807667558,"remaining_time":38.89840115},
{"learn":[0.2835679944],"iteration":110,"passed_time":4.840449183,"remaining_time":38.76720111},
{"learn":[0.2830727495],"iteration":111,"passed_time":4.892317066,"remaining_time":38.78908531},
{"learn":[0.2827472655],"iteration":112,"passed_time":4.929118145,"remaining_time":38.69139641},
{"learn":[0.2824597819],"iteration":113,"passed_time":4.960010433,"remaining_time":38.54885301},
{"learn":[0.2819745809],"iteration":114,"passed_time":4.999147416,"remaining_time":38.47169968},
{"learn":[0.281531899],"iteration":115,"passed_time":5.032271963,"remaining_time":38.34938289},
{"learn":[0.2812923679],"iteration":116,"passed_time":5.07106688,"remaining_time":38.27138509},
{"learn":[0.2810350666],"iteration":117,"passed_time":5.125369316,"remaining_time":38.30996387},
{"learn":[0.2806796229],"iteration":118,"passed_time":5.163456644,"remaining_time":38.22693532},
{"learn":[0.2803627957],"iteration":119,"passed_time":5.200382895,"remaining_time":38.13614123},
{"learn":[0.2799763015],"iteration":120,"passed_time":5.243951676,"remaining_time":38.09449193},
{"learn":[0.2795954849],"iteration":121,"passed_time":5.282528886,"remaining_time":38.01688822},
{"learn":[0.2792157472],"iteration":122,"passed_time":5.315624276,"remaining_time":37.90083325},
{"learn":[0.2787781151],"iteration":123,"passed_time":5.346971135,"remaining_time":37.77376382},
{"learn":[0.2785253331],"iteration":124,"passed_time":5.384909782,"remaining_time":37.69436847},
{"learn":[0.2781104849],"iteration":125,"passed_time":5.416556599,"remaining_time":37.57198784},
{"learn":[0.2777548451],"iteration":126,"passed_time":5.447496064,"remaining_time":37.44617373},
{"learn":[0.2773996823],"iteration":127,"passed_time":5.488413298,"remaining_time":37.38981559},
{"learn":[0.2771626644],"iteration":128,"passed_time":5.529377644,"remaining_time":37.33401495},
{"learn":[0.276529194],"iteration":129,"passed_time":5.562324657,"remaining_time":37.22478809},
{"learn":[0.2762513025],"iteration":130,"passed_time":5.596710329,"remaining_time":37.12626928},
{"learn":[0.2759565049],"iteration":131,"passed_time":5.630335558,"remaining_time":37.0237217},
{"learn":[0.2755808377],"iteration":132,"passed_time":5.662730185,"remaining_time":36.9141885},
{"learn":[0.2752834141],"iteration":133,"passed_time":5.695303348,"remaining_time":36.80696044},
{"learn":[0.2749568133],"iteration":134,"passed_time":5.725524904,"remaining_time":36.68577068},
{"learn":[0.2747124439],"iteration":135,"passed_time":5.755491564,"remaining_time":36.56429935},
{"learn":[0.2743174769],"iteration":136,"passed_time":5.791480656,"remaining_time":36.48210077},
{"learn":[0.2738938612],"iteration":137,"passed_time":5.819502068,"remaining_time":36.35080277},
{"learn":[0.273578314],"iteration":138,"passed_time":5.849909283,"remaining_time":36.23576901},
{"learn":[0.2733178433],"iteration":139,"passed_time":5.895324398,"remaining_time":36.21413559},
{"learn":[0.272996068],"iteration":140,"passed_time":5.939586667,"remaining_time":36.18514147},
{"learn":[0.2726463422],"iteration":141,"passed_time":5.971652862,"remaining_time":36.08224053},
{"learn":[0.2717728926],"iteration":142,"passed_time":6.008389408,"remaining_time":36.00831974},
{"learn":[0.2715081735],"iteration":143,"passed_time":6.039637351,"remaining_time":35.9022887},
{"learn":[0.2713078229],"iteration":144,"passed_time":6.071359942,"remaining_time":35.80008793},
{"learn":[0.2710944811],"iteration":145,"passed_time":6.109857636,"remaining_time":35.73848234},
{"learn":[0.2707107654],"iteration":146,"passed_time":6.142652262,"remaining_time":35.64409782},
{"learn":[0.2704960519],"iteration":147,"passed_time":6.173296891,"remaining_time":35.53816859},
{"learn":[0.2702589753],"iteration":148,"passed_time":6.207915641,"remaining_time":35.45594772},
{"learn":[0.2699183067],"iteration":149,"passed_time":6.240500573,"remaining_time":35.36283658},
{"learn":[0.2696027098],"iteration":150,"passed_time":6.271191195,"remaining_time":35.25987632},
{"learn":[0.2694066404],"iteration":151,"passed_time":6.304961832,"remaining_time":35.17505022},
{"learn":[0.2691674096],"iteration":152,"passed_time":6.336294659,"remaining_time":35.07739592},
{"learn":[0.2686753482],"iteration":153,"passed_time":6.389239415,"remaining_time":35.09932822},
{"learn":[0.2684099003],"iteration":154,"passed_time":6.419380989,"remaining_time":34.99598023},
{"learn":[0.2680987143],"iteration":155,"passed_time":6.449427449,"remaining_time":34.8930562},
{"learn":[0.2677795809],"iteration":156,"passed_time":6.485027405,"remaining_time":34.82087964},
{"learn":[0.2675050965],"iteration":157,"passed_time":6.51739358,"remaining_time":34.73193287},
{"learn":[0.2673668947],"iteration":158,"passed_time":6.544634965,"remaining_time":34.61659123},
{"learn":[0.2671854478],"iteration":159,"passed_time":6.574593904,"remaining_time":34.51661799},
{"learn":[0.266917044],"iteration":160,"passed_time":6.607210805,"remaining_time":34.43136562},
{"learn":[0.266505985],"iteration":161,"passed_time":6.637642874,"remaining_time":34.33546129},
{"learn":[0.2661502427],"iteration":162,"passed_time":6.666557451,"remaining_time":34.23256802},
{"learn":[0.26584015],"iteration":163,"passed_time":6.702134572,"remaining_time":34.16453965},
{"learn":[0.2655244718],"iteration":164,"passed_time":6.732486206,"remaining_time":34.07046049},
{"learn":[0.26526437],"iteration":165,"passed_time":6.77638581,"remaining_time":34.04521546},
{"learn":[0.2650444502],"iteration":166,"passed_time":6.807516387,"remaining_time":33.95605479},
{"learn":[0.2648423748],"iteration":167,"passed_time":6.837769303,"remaining_time":33.86323846},
{"learn":[0.2644718347],"iteration":168,"passed_time":6.868937687,"remaining_time":33.77566401},
{"learn":[0.2641292336],"iteration":169,"passed_time":6.903611265,"remaining_time":33.70586676},
{"learn":[0.2638566521],"iteration":170,"passed_time":6.9332078,"remaining_time":33.61186705},
{"learn":[0.2636024695],"iteration":171,"passed_time":6.964991859,"remaining_time":33.52914686},
{"learn":[0.2631923147],"iteration":172,"passed_time":7.001376196,"remaining_time":33.46900644},
{"learn":[0.2629146556],"iteration":173,"passed_time":7.03561548,"remaining_time":33.39895625},
{"learn":[0.2627431876],"iteration":174,"passed_time":7.068911813,"remaining_time":33.32486998},
{"learn":[0.262473842],"iteration":175,"passed_time":7.102961353,"remaining_time":33.25477361},
{"learn":[0.2622383148],"iteration":176,"passed_time":7.134391829,"remaining_time":33.17290664},
{"learn":[0.2617884942],"iteration":177,"passed_time":7.17258715,"remaining_time":33.12284628},
{"learn":[0.2615416499],"iteration":178,"passed_time":7.224048891,"remaining_time":33.13376614},
{"learn":[0.2613670252],"iteration":179,"passed_time":7.255798455,"remaining_time":33.05419296},
{"learn":[0.2609794896],"iteration":180,"passed_time":7.294626078,"remaining_time":33.00717546},
{"learn":[0.2606503009],"iteration":181,"passed_time":7.323834402,"remaining_time":32.91701396},
{"learn":[0.2602994333],"iteration":182,"passed_time":7.360762022,"remaining_time":32.86198127},
{"learn":[0.2600738049],"iteration":183,"passed_time":7.397038768,"remaining_time":32.80425888},
{"learn":[0.2597483274],"iteration":184,"passed_time":7.427331364,"remaining_time":32.72040574},
{"learn":[0.2595974953],"iteration":185,"passed_time":7.457191839,"remaining_time":32.6352374},
{"learn":[0.2592667388],"iteration":186,"passed_time":7.495857695,"remaining_time":32.58894281},
{"learn":[0.2590139916],"iteration":187,"passed_time":7.523708446,"remaining_time":32.49601733},
{"learn":[0.2587203805],"iteration":188,"passed_time":7.556901734,"remaining_time":32.42670533},
{"learn":[0.2585065544],"iteration":189,"passed_time":7.595452432,"remaining_time":32.380613},
{"learn":[0.258188324],"iteration":190,"passed_time":7.638963281,"remaining_time":32.35560887},
{"learn":[0.2576799691],"iteration":191,"passed_time":7.66945049,"remaining_time":32.27560414},
{"learn":[0.2573821728],"iteration":192,"passed_time":7.707385764,"remaining_time":32.2272555},
{"learn":[0.2572486068],"iteration":193,"passed_time":7.740371832,"remaining_time":32.15845204},
{"learn":[0.2569575979],"iteration":194,"passed_time":7.773715103,"remaining_time":32.09149055},
{"learn":[0.2568081337],"iteration":195,"passed_time":7.807342153,"remaining_time":32.02603618},
{"learn":[0.2563620716],"iteration":196,"passed_time":7.839151005,"remaining_time":31.95349369},
{"learn":[0.2561258427],"iteration":197,"passed_time":7.870179466,"remaining_time":31.87820167},
{"learn":[0.2559336178],"iteration":198,"passed_time":7.905158671,"remaining_time":31.81925676},
{"learn":[0.2557721144],"iteration":199,"passed_time":7.936308668,"remaining_time":31.74523467},
{"learn":[0.2555145083],"iteration":200,"passed_time":7.968538524,"remaining_time":31.67593174},
{"learn":[0.2551920231],"iteration":201,"passed_time":8.01532227,"remaining_time":31.66449095},
{"learn":[0.2547512544],"iteration":202,"passed_time":8.056991795,"remaining_time":31.63262296},
{"learn":[0.2543243814],"iteration":203,"passed_time":8.107757147,"remaining_time":31.63615044},
{"learn":[0.2540652442],"iteration":204,"passed_time":8.140188837,"remaining_time":31.56804939},
{"learn":[0.2538791221],"iteration":205,"passed_time":8.174093567,"remaining_time":31.50597229},
{"learn":[0.2535374469],"iteration":206,"passed_time":8.20757506,"remaining_time":31.442546},
{"learn":[0.2532311419],"iteration":207,"passed_time":8.240910731,"remaining_time":31.3788524},
{"learn":[0.2530873116],"iteration":208,"passed_time":8.27119801,"remaining_time":31.30391209},
{"learn":[0.2528616197],"iteration":209,"passed_time":8.305625678,"remaining_time":31.24497279},
{"learn":[0.2526282332],"iteration":210,"passed_time":8.337624145,"remaining_time":31.17718223},
{"learn":[0.25243646],"iteration":211,"passed_time":8.370075408,"remaining_time":31.11141236},
{"learn":[0.2522468009],"iteration":212,"passed_time":8.412881385,"remaining_time":31.08421432},
{"learn":[0.2521014866],"iteration":213,"passed_time":8.450350997,"remaining_time":31.03727048},
{"learn":[0.2520060621],"iteration":214,"passed_time":8.485668198,"remaining_time":30.98255598},
{"learn":[0.2517719893],"iteration":215,"passed_time":8.513456635,"remaining_time":30.90069445},
{"learn":[0.2516365505],"iteration":216,"passed_time":8.544293175,"remaining_time":30.83032975},
{"learn":[0.2514959614],"iteration":217,"passed_time":8.582672934,"remaining_time":30.7873864},
{"learn":[0.2511921146],"iteration":218,"passed_time":8.613513198,"remaining_time":30.71759729},
{"learn":[0.2508433017],"iteration":219,"passed_time":8.645976898,"remaining_time":30.65391809},
{"learn":[0.250611379],"iteration":220,"passed_time":8.681367951,"remaining_time":30.60083997},
{"learn":[0.2504541998],"iteration":221,"passed_time":8.709362378,"remaining_time":30.52199968},
{"learn":[0.2503157844],"iteration":222,"passed_time":8.740852879,"remaining_time":30.4557968},
{"learn":[0.2502114567],"iteration":223,"passed_time":8.770999771,"remaining_time":30.38524921},
{"learn":[0.2500132473],"iteration":224,"passed_time":8.808558018,"remaining_time":30.34058873},
{"learn":[0.2497695328],"iteration":225,"passed_time":8.851077063,"remaining_time":30.31298074},
{"learn":[0.2496505873],"iteration":226,"passed_time":8.887213985,"remaining_time":30.26350842},
{"learn":[0.2494920726],"iteration":227,"passed_time":8.917329074,"remaining_time":30.19376336},
{"learn":[0.2493323885],"iteration":228,"passed_time":8.951641715,"remaining_time":30.13849678},
{"learn":[0.2492245489],"iteration":229,"passed_time":8.988624569,"remaining_time":30.09235182},
{"learn":[0.2488660734],"iteration":230,"passed_time":9.023706325,"remaining_time":30.03995742},
{"learn":[0.2486204668],"iteration":231,"passed_time":9.057050708,"remaining_time":29.98196097},
{"learn":[0.2484541088],"iteration":232,"passed_time":9.091738357,"remaining_time":29.92859794},
{"learn":[0.2481394346],"iteration":233,"passed_time":9.123686465,"remaining_time":29.86642663},
{"learn":[0.2479844888],"iteration":234,"passed_time":9.155973196,"remaining_time":29.80561487},
{"learn":[0.2478121057],"iteration":235,"passed_time":9.191704649,"remaining_time":29.75619641},
{"learn":[0.247593889],"iteration":236,"passed_time":9.235060754,"remaining_time":29.73144032},
{"learn":[0.2473947162],"iteration":237,"passed_time":9.267041874,"remaining_time":29.67010886},
{"learn":[0.247214741],"iteration":238,"passed_time":9.303908086,"remaining_time":29.62457763},
{"learn":[0.2470227382],"iteration":239,"passed_time":9.334778569,"remaining_time":29.56013214},
{"learn":[0.2468346334],"iteration":240,"passed_time":9.370004104,"remaining_time":29.50968097},
{"learn":[0.2466605628],"iteration":241,"passed_time":9.406737283,"remaining_time":29.46407793},
{"learn":[0.2465617938],"iteration":242,"passed_time":9.437977826,"remaining_time":29.40143709},
{"learn":[0.2463701419],"iteration":243,"passed_time":9.470614637,"remaining_time":29.34337978},
{"learn":[0.2460909903],"iteration":244,"passed_time":9.508557908,"remaining_time":29.30188253},
{"learn":[0.2458314594],"iteration":245,"passed_time":9.540920317,"remaining_time":29.24330861},
{"learn":[0.2456357706],"iteration":246,"passed_time":9.572686376,"remaining_time":29.18312891},
{"learn":[0.2454595007],"iteration":247,"passed_time":9.629421998,"remaining_time":29.19889251},
{"learn":[0.2453236204],"iteration":248,"passed_time":9.661003189,"remaining_time":29.13820641},
{"learn":[0.2450831491],"iteration":249,"passed_time":9.696418235,"remaining_time":29.0892547},
{"learn":[0.244905436],"iteration":250,"passed_time":9.727533227,"remaining_time":29.02757923},
{"learn":[0.2446585132],"iteration":251,"passed_time":9.76197752,"remaining_time":28.97602851},
{"learn":[0.2444307286],"iteration":252,"passed_time":9.797632565,"remaining_time":28.92818785},
{"learn":[0.2442143845],"iteration":253,"passed_time":9.829037174,"remaining_time":28.86795957},
{"learn":[0.2437867114],"iteration":254,"passed_time":9.861706791,"remaining_time":28.81165317},
{"learn":[0.2435217622],"iteration":255,"passed_time":9.900315218,"remaining_time":28.7727911},
{"learn":[0.2433024946],"iteration":256,"passed_time":9.929966378,"remaining_time":28.70803509},
{"learn":[0.2430296712],"iteration":257,"passed_time":9.960765653,"remaining_time":28.64685316},
{"learn":[0.2429143529],"iteration":258,"passed_time":10.00335436,"remaining_time":28.61963544},
{"learn":[0.2427561902],"iteration":259,"passed_time":10.04536854,"remaining_time":28.59066431},
{"learn":[0.2425479318],"iteration":260,"passed_time":10.08400479,"remaining_time":28.55202888},
{"learn":[0.2424421168],"iteration":261,"passed_time":10.11488101,"remaining_time":28.49153505},
{"learn":[0.242217374],"iteration":262,"passed_time":10.14481245,"remaining_time":28.42861892},
{"learn":[0.2420494695],"iteration":263,"passed_time":10.18472954,"remaining_time":28.39379145},
{"learn":[0.2419101707],"iteration":264,"passed_time":10.21523014,"remaining_time":28.33280813},
{"learn":[0.2416663598],"iteration":265,"passed_time":10.24935569,"remaining_time":28.28205668},
{"learn":[0.2414151285],"iteration":266,"passed_time":10.28540418,"remaining_time":28.23670884},
{"learn":[0.241231466],"iteration":267,"passed_time":10.31846899,"remaining_time":28.18328096},
{"learn":[0.2409349053],"iteration":268,"passed_time":10.34962666,"remaining_time":28.12482188},
{"learn":[0.2406544925],"iteration":269,"passed_time":10.38588729,"remaining_time":28.08036192},
{"learn":[0.2404701282],"iteration":270,"passed_time":10.43310067,"remaining_time":28.06542579},
{"learn":[0.2403205765],"iteration":271,"passed_time":10.46464777,"remaining_time":28.00832198},
{"learn":[0.2402059839],"iteration":272,"passed_time":10.50062108,"remaining_time":27.9631924},
{"learn":[0.2400216213],"iteration":273,"passed_time":10.53316321,"remaining_time":27.90903828},
{"learn":[0.2398132288],"iteration":274,"passed_time":10.56685578,"remaining_time":27.85807434},
{"learn":[0.2395349807],"iteration":275,"passed_time":10.60440952,"remaining_time":27.81736411},
{"learn":[0.2393111616],"iteration":276,"passed_time":10.63592027,"remaining_time":27.76090382},
{"learn":[0.2391020775],"iteration":277,"passed_time":10.66967804,"remaining_time":27.71045879},
{"learn":[0.238895479],"iteration":278,"passed_time":10.70576226,"remaining_time":27.66614549},
{"learn":[0.2386682356],"iteration":279,"passed_time":10.73825687,"remaining_time":27.61266051},
{"learn":[0.2384874609],"iteration":280,"passed_time":10.77083947,"remaining_time":27.55955011},
{"learn":[0.2383506368],"iteration":281,"passed_time":10.80376018,"remaining_time":27.50744614},
{"learn":[0.2380737918],"iteration":282,"passed_time":10.8352104,"remaining_time":27.45175215},
{"learn":[0.2378801305],"iteration":283,"passed_time":10.88365697,"remaining_time":27.43907884},
{"learn":[0.2376646789],"iteration":284,"passed_time":10.91570338,"remaining_time":27.38501024},
{"learn":[0.2374122722],"iteration":285,"passed_time":10.94730029,"remaining_time":27.32997344},
{"learn":[0.237198487],"iteration":286,"passed_time":10.9869084,"remaining_time":27.29500239},
{"learn":[0.2369756965],"iteration":287,"passed_time":11.03056401,"remaining_time":27.27000548},
{"learn":[0.2368446318],"iteration":288,"passed_time":11.06482406,"remaining_time":27.22176439},
{"learn":[0.2366762416],"iteration":289,"passed_time":11.09962454,"remaining_time":27.17494284},
{"learn":[0.2365170772],"iteration":290,"passed_time":11.13065885,"remaining_time":27.11902793},
{"learn":[0.2363455517],"iteration":291,"passed_time":11.16278706,"remaining_time":27.06593574},
{"learn":[0.2361744236],"iteration":292,"passed_time":11.1965612,"remaining_time":27.01695826},
{"learn":[0.2361001666],"iteration":293,"passed_time":11.2266681,"remaining_time":26.95927783},
{"learn":[0.2358086377],"iteration":294,"passed_time":11.26321604,"remaining_time":26.91717731},
{"learn":[0.2357026637],"iteration":295,"passed_time":11.30863731,"remaining_time":26.89621847},
{"learn":[0.2354706758],"iteration":296,"passed_time":11.33918744,"remaining_time":26.83989484},
{"learn":[0.2352633617],"iteration":297,"passed_time":11.36919973,"remaining_time":26.78247721},
{"learn":[0.2351518908],"iteration":298,"passed_time":11.40902716,"remaining_time":26.74825431},
{"learn":[0.2348892792],"iteration":299,"passed_time":11.44224224,"remaining_time":26.69856523},
{"learn":[0.2346616889],"iteration":300,"passed_time":11.47476416,"remaining_time":26.6473759},
{"learn":[0.2344230052],"iteration":301,"passed_time":11.50945329,"remaining_time":26.6013192},
{"learn":[0.2342333611],"iteration":302,"passed_time":11.54105294,"remaining_time":26.5482307},
{"learn":[0.2341065527],"iteration":303,"passed_time":11.5713682,"remaining_time":26.49234299},
{"learn":[0.2339921309],"iteration":304,"passed_time":11.6055599,"remaining_time":26.44545616},
{"learn":[0.2338379187],"iteration":305,"passed_time":11.64081095,"remaining_time":26.4010549},
{"learn":[0.2334714882],"iteration":306,"passed_time":11.68787188,"remaining_time":26.38337204},
{"learn":[0.2333644981],"iteration":307,"passed_time":11.71919007,"remaining_time":26.33012835},
{"learn":[0.233156562],"iteration":308,"passed_time":11.7515232,"remaining_time":26.27929622},
{"learn":[0.2329903094],"iteration":309,"passed_time":11.78739597,"remaining_time":26.23646199},
{"learn":[0.232734774],"iteration":310,"passed_time":11.81943961,"remaining_time":26.18518935},
{"learn":[0.2326094495],"iteration":311,"passed_time":11.85045849,"remaining_time":26.13178027},
{"learn":[0.2322670089],"iteration":312,"passed_time":11.88407477,"remaining_time":26.08421522},
{"learn":[0.2320541555],"iteration":313,"passed_time":11.91597384,"remaining_time":26.03298743},
{"learn":[0.2319472284],"iteration":314,"passed_time":11.9469572,"remaining_time":25.97989105},
{"learn":[0.2317628522],"iteration":315,"passed_time":11.98527052,"remaining_time":25.94280075},
{"learn":[0.2316065957],"iteration":316,"passed_time":12.01696885,"remaining_time":25.89145024},
{"learn":[0.2313831423],"iteration":317,"passed_time":12.06732441,"remaining_time":25.88023662},
{"learn":[0.2311741321],"iteration":318,"passed_time":12.09707169,"remaining_time":25.82478315},
{"learn":[0.2310673187],"iteration":319,"passed_time":12.12841042,"remaining_time":25.77287215},
{"learn":[0.2307643318],"iteration":320,"passed_time":12.16661868,"remaining_time":25.7356202},
{"learn":[0.2306529843],"iteration":321,"passed_time":12.19602092,"remaining_time":25.67982045},
{"learn":[0.2304746232],"iteration":322,"passed_time":12.22632846,"remaining_time":25.62608163},
{"learn":[0.2302892986],"iteration":323,"passed_time":12.27109595,"remaining_time":25.60265697},
{"learn":[0.2301905916],"iteration":324,"passed_time":12.31246461,"remaining_time":25.57204187},
{"learn":[0.2300821819],"iteration":325,"passed_time":12.35951028,"remaining_time":25.55309793},
{"learn":[0.2298801292],"iteration":326,"passed_time":12.39409149,"remaining_time":25.50832897},
{"learn":[0.2296363354],"iteration":327,"passed_time":12.43045059,"remaining_time":25.46726463},
{"learn":[0.2294924761],"iteration":328,"passed_time":12.47240145,"remaining_time":25.43763335},
{"learn":[0.2292163641],"iteration":329,"passed_time":12.5206352,"remaining_time":25.42068359},
{"learn":[0.2290813624],"iteration":330,"passed_time":12.55880157,"remaining_time":25.38319713},
{"learn":[0.2288599513],"iteration":331,"passed_time":12.59237391,"remaining_time":25.33646317},
{"learn":[0.2284968617],"iteration":332,"passed_time":12.62843472,"remaining_time":25.29479266},
{"learn":[0.2283352986],"iteration":333,"passed_time":12.66275323,"remaining_time":25.24968159},
{"learn":[0.2280344208],"iteration":334,"passed_time":12.71324646,"remaining_time":25.23674297},
{"learn":[0.2277812892],"iteration":335,"passed_time":12.75019051,"remaining_time":25.19680506},
{"learn":[0.2276117409],"iteration":336,"passed_time":12.79202699,"remaining_time":25.16651008},
{"learn":[0.2274767432],"iteration":337,"passed_time":12.82815324,"remaining_time":25.12496285},
{"learn":[0.2271923518],"iteration":338,"passed_time":12.86434975,"remaining_time":25.08358462},
{"learn":[0.2269121649],"iteration":339,"passed_time":12.90849254,"remaining_time":25.05766199},
{"learn":[0.2264697441],"iteration":340,"passed_time":12.96402856,"remaining_time":25.0536505},
{"learn":[0.2261433578],"iteration":341,"passed_time":12.99640105,"remaining_time":25.00477161},
{"learn":[0.2259299076],"iteration":342,"passed_time":13.03190831,"remaining_time":24.96199346},
{"learn":[0.2257075132],"iteration":343,"passed_time":13.07374236,"remaining_time":24.93132264},
{"learn":[0.2253464493],"iteration":344,"passed_time":13.11403385,"remaining_time":24.89765846},
{"learn":[0.2250450506],"iteration":345,"passed_time":13.14979777,"remaining_time":24.8553981},
{"learn":[0.2247984337],"iteration":346,"passed_time":13.18807445,"remaining_time":24.81790378},
{"learn":[0.2246100912],"iteration":347,"passed_time":13.22670746,"remaining_time":24.7810726},
{"learn":[0.2244861101],"iteration":348,"passed_time":13.26467825,"remaining_time":24.74299582},
{"learn":[0.2242696841],"iteration":349,"passed_time":13.29749231,"remaining_time":24.69534286},
{"learn":[0.2241070248],"iteration":350,"passed_time":13.34195691,"remaining_time":24.66931633},
{"learn":[0.2238459407],"iteration":351,"passed_time":13.38085836,"remaining_time":24.63294381},
{"learn":[0.2237059357],"iteration":352,"passed_time":13.42377773,"remaining_time":24.60392122},
{"learn":[0.2235766894],"iteration":353,"passed_time":13.46641313,"remaining_time":24.57430193},
{"learn":[0.2233863786],"iteration":354,"passed_time":13.50686534,"remaining_time":24.54064265},
{"learn":[0.2232675972],"iteration":355,"passed_time":13.55261713,"remaining_time":24.51653211},
{"learn":[0.2231673815],"iteration":356,"passed_time":13.59026319,"remaining_time":24.47770093},
{"learn":[0.2230563614],"iteration":357,"passed_time":13.630265,"remaining_time":24.44310091},
{"learn":[0.2228527704],"iteration":358,"passed_time":13.66681112,"remaining_time":24.40230064},
{"learn":[0.2226337366],"iteration":359,"passed_time":13.70491734,"remaining_time":24.36429749},
{"learn":[0.2224731204],"iteration":360,"passed_time":13.78236287,"remaining_time":24.39592762},
{"learn":[0.2223075081],"iteration":361,"passed_time":13.82564603,"remaining_time":24.36674632},
{"learn":[0.2222196186],"iteration":362,"passed_time":13.86753904,"remaining_time":24.33504785},
{"learn":[0.2219998919],"iteration":363,"passed_time":13.90239792,"remaining_time":24.29100296},
{"learn":[0.2217159242],"iteration":364,"passed_time":13.93803694,"remaining_time":24.24836563},
{"learn":[0.2213657634],"iteration":365,"passed_time":13.98028781,"remaining_time":24.21721986},
{"learn":[0.2212123083],"iteration":366,"passed_time":14.01434849,"remaining_time":24.17188719},
{"learn":[0.2210548395],"iteration":367,"passed_time":14.05033089,"remaining_time":24.12991609},
{"learn":[0.220902339],"iteration":368,"passed_time":14.08481801,"remaining_time":24.08542049},
{"learn":[0.2207365137],"iteration":369,"passed_time":14.12270934,"remaining_time":24.04677536},
{"learn":[0.2205793863],"iteration":370,"passed_time":14.15853314,"remaining_time":24.00462896},
{"learn":[0.2203371246],"iteration":371,"passed_time":14.20472571,"remaining_time":23.98002082},
{"learn":[0.2202129138],"iteration":372,"passed_time":14.23855018,"remaining_time":23.93450661},
{"learn":[0.2199192356],"iteration":373,"passed_time":14.27520014,"remaining_time":23.89378419},
{"learn":[0.2196887314],"iteration":374,"passed_time":14.30651442,"remaining_time":23.84419071},
{"learn":[0.2194668259],"iteration":375,"passed_time":14.34973975,"remaining_time":23.81446172},
{"learn":[0.2193282923],"iteration":376,"passed_time":14.38284977,"remaining_time":23.76794538},
{"learn":[0.2191294066],"iteration":377,"passed_time":14.42116632,"remaining_time":23.73006733},
{"learn":[0.218986395],"iteration":378,"passed_time":14.45953275,"remaining_time":23.6922687},
{"learn":[0.21880488],"iteration":379,"passed_time":14.49395109,"remaining_time":23.64802546},
{"learn":[0.2186782568],"iteration":380,"passed_time":14.52900208,"remaining_time":23.60486164},
{"learn":[0.2185740262],"iteration":381,"passed_time":14.56560599,"remaining_time":23.56425262},
{"learn":[0.2183754308],"iteration":382,"passed_time":14.6134206,"remaining_time":23.54172458},
{"learn":[0.2181729037],"iteration":383,"passed_time":14.65362505,"remaining_time":23.50685684},
{"learn":[0.2179270763],"iteration":384,"passed_time":14.69184742,"remaining_time":23.46879523},
{"learn":[0.2178148553],"iteration":385,"passed_time":14.73525902,"remaining_time":23.43898715},
{"learn":[0.2176534702],"iteration":386,"passed_time":14.77403405,"remaining_time":23.40176453},
{"learn":[0.2175132634],"iteration":387,"passed_time":14.81038226,"remaining_time":23.36070604},
{"learn":[0.2173816258],"iteration":388,"passed_time":14.84641431,"remaining_time":23.31917517},
{"learn":[0.2170855164],"iteration":389,"passed_time":14.88470923,"remaining_time":23.28121187},
{"learn":[0.2169584345],"iteration":390,"passed_time":14.91953181,"remaining_time":23.23783855},
{"learn":[0.21684527],"iteration":391,"passed_time":14.96188405,"remaining_time":23.2061875},
{"learn":[0.216617084],"iteration":392,"passed_time":15.0084363,"remaining_time":23.18096905},
{"learn":[0.2163340465],"iteration":393,"passed_time":15.04947165,"remaining_time":23.14715691},
{"learn":[0.2162302343],"iteration":394,"passed_time":15.08685545,"remaining_time":23.10771531},
{"learn":[0.2161058585],"iteration":395,"passed_time":15.12291311,"remaining_time":23.06626141},
{"learn":[0.2159364318],"iteration":396,"passed_time":15.16669879,"remaining_time":23.03657272},
{"learn":[0.215786976],"iteration":397,"passed_time":15.20205049,"remaining_time":22.99405628},
{"learn":[0.2156583664],"iteration":398,"passed_time":15.23617566,"remaining_time":22.94972825},
{"learn":[0.2155354949],"iteration":399,"passed_time":15.27434591,"remaining_time":22.91151886},
{"learn":[0.2153721422],"iteration":400,"passed_time":15.30668564,"remaining_time":22.86460025},
{"learn":[0.2151912219],"iteration":401,"passed_time":15.34101164,"remaining_time":22.82070886},
{"learn":[0.215015667],"iteration":402,"passed_time":15.37992928,"remaining_time":22.78366696},
{"learn":[0.2148019197],"iteration":403,"passed_time":15.41584832,"remaining_time":22.74219207},
{"learn":[0.2146535171],"iteration":404,"passed_time":15.46844619,"remaining_time":22.72524811},
{"learn":[0.2144348587],"iteration":405,"passed_time":15.50598534,"remaining_time":22.68609679},
{"learn":[0.2142302074],"iteration":406,"passed_time":15.53937531,"remaining_time":22.64090801},
{"learn":[0.2140707522],"iteration":407,"passed_time":15.58008747,"remaining_time":22.60640143},
{"learn":[0.2139396371],"iteration":408,"passed_time":15.61592436,"remaining_time":22.56481979},
{"learn":[0.2137485035],"iteration":409,"passed_time":15.64925464,"remaining_time":22.51965911},
{"learn":[0.2136254713],"iteration":410,"passed_time":15.68941387,"remaining_time":22.48434251},
{"learn":[0.2133781898],"iteration":411,"passed_time":15.72448378,"remaining_time":22.44173899},
{"learn":[0.2132039195],"iteration":412,"passed_time":15.7650847,"remaining_time":22.40703321},
{"learn":[0.2130401547],"iteration":413,"passed_time":15.80038263,"remaining_time":22.36479281},
{"learn":[0.2129244165],"iteration":414,"passed_time":15.84839805,"remaining_time":22.34051291},
{"learn":[0.2127610263],"iteration":415,"passed_time":15.89350159,"remaining_time":22.31203108},
{"learn":[0.2126488201],"iteration":416,"passed_time":15.93596885,"remaining_time":22.27978378},
{"learn":[0.2125256275],"iteration":417,"passed_time":15.97382949,"remaining_time":22.24107359},
{"learn":[0.2123944793],"iteration":418,"passed_time":16.02302738,"remaining_time":22.21808808},
{"learn":[0.2123030183],"iteration":419,"passed_time":16.0645629,"remaining_time":22.18439638},
{"learn":[0.2121020388],"iteration":420,"passed_time":16.10529275,"remaining_time":22.14955939},
{"learn":[0.2118276364],"iteration":421,"passed_time":16.14042337,"remaining_time":22.10702538},
{"learn":[0.2116918655],"iteration":422,"passed_time":16.17999367,"remaining_time":22.07058238},
{"learn":[0.2115643872],"iteration":423,"passed_time":16.21360978,"remaining_time":22.02603593},
{"learn":[0.2110786949],"iteration":424,"passed_time":16.26088562,"remaining_time":22.00002172},
{"learn":[0.2108596857],"iteration":425,"passed_time":16.30298232,"remaining_time":21.96692923},
{"learn":[0.2106618967],"iteration":426,"passed_time":16.33880164,"remaining_time":21.92537082},
{"learn":[0.2103952957],"iteration":427,"passed_time":16.37834147,"remaining_time":21.88881149},
{"learn":[0.2102263077],"iteration":428,"passed_time":16.41844901,"remaining_time":21.85299391},
{"learn":[0.2100203241],"iteration":429,"passed_time":16.46660052,"remaining_time":21.82781929},
{"learn":[0.2099066821],"iteration":430,"passed_time":16.50363773,"remaining_time":21.78786513},
{"learn":[0.2097817495],"iteration":431,"passed_time":16.54005469,"remaining_time":21.74710894},
{"learn":[0.2096434283],"iteration":432,"passed_time":16.57917624,"remaining_time":21.70991438},
{"learn":[0.2095746422],"iteration":433,"passed_time":16.61182999,"remaining_time":21.66427598},
{"learn":[0.209492475],"iteration":434,"passed_time":16.64566045,"remaining_time":21.62022564},
{"learn":[0.2093686441],"iteration":435,"passed_time":16.68482496,"remaining_time":21.58312219},
{"learn":[0.2092849881],"iteration":436,"passed_time":16.7298557,"remaining_time":21.55356695},
{"learn":[0.2091460585],"iteration":437,"passed_time":16.76755565,"remaining_time":21.51453488},
{"learn":[0.2089786205],"iteration":438,"passed_time":16.80196754,"remaining_time":21.47130704},
{"learn":[0.2087765147],"iteration":439,"passed_time":16.83643417,"remaining_time":21.42818895},
{"learn":[0.2086427286],"iteration":440,"passed_time":16.87861733,"remaining_time":21.39489135},
{"learn":[0.2084317476],"iteration":441,"passed_time":16.92166859,"remaining_time":21.36264949},
{"learn":[0.2082363966],"iteration":442,"passed_time":17.12066355,"remaining_time":21.5264325},
{"learn":[0.2081230612],"iteration":443,"passed_time":17.2631165,"remaining_time":21.61777651},
{"learn":[0.2079796543],"iteration":444,"passed_time":17.42475919,"remaining_time":21.73200304},
{"learn":[0.207851763],"iteration":445,"passed_time":17.49551053,"remaining_time":21.73209156},
{"learn":[0.2077302262],"iteration":446,"passed_time":17.5301768,"remaining_time":21.68722096},
{"learn":[0.2075987853],"iteration":447,"passed_time":17.56484998,"remaining_time":21.64240444},
{"learn":[0.2074569716],"iteration":448,"passed_time":17.60075156,"remaining_time":21.59914056},
{"learn":[0.2073241842],"iteration":449,"passed_time":17.63381211,"remaining_time":21.55243702},
{"learn":[0.207229213],"iteration":450,"passed_time":17.6671184,"remaining_time":21.50609313},
{"learn":[0.2071098702],"iteration":451,"passed_time":17.7019466,"remaining_time":21.46165207},
{"learn":[0.2069956086],"iteration":452,"passed_time":17.74994672,"remaining_time":21.43315863},
{"learn":[0.2068967793],"iteration":453,"passed_time":17.7864712,"remaining_time":21.39077814},
{"learn":[0.2067631958],"iteration":454,"passed_time":17.82193556,"remaining_time":21.34715358},
{"learn":[0.2066408408],"iteration":455,"passed_time":17.86675565,"remaining_time":21.31472604},
{"learn":[0.2065388155],"iteration":456,"passed_time":17.91465854,"remaining_time":21.28590719},
{"learn":[0.2064564512],"iteration":457,"passed_time":17.95048302,"remaining_time":21.24271134},
{"learn":[0.2063298865],"iteration":458,"passed_time":17.98680122,"remaining_time":21.20012954},
{"learn":[0.2061274523],"iteration":459,"passed_time":18.02466009,"remaining_time":21.15938358},
{"learn":[0.2060113649],"iteration":460,"passed_time":18.05910767,"remaining_time":21.11466168},
{"learn":[0.2058992307],"iteration":461,"passed_time":18.09576165,"remaining_time":21.07255361},
{"learn":[0.2056146504],"iteration":462,"passed_time":18.14436559,"remaining_time":21.04432899},
{"learn":[0.2053659916],"iteration":463,"passed_time":18.18101807,"remaining_time":21.00221053},
{"learn":[0.2052541435],"iteration":464,"passed_time":18.2167576,"remaining_time":20.95906519},
{"learn":[0.2051507486],"iteration":465,"passed_time":18.2517879,"remaining_time":20.91513892},
{"learn":[0.2050691852],"iteration":466,"passed_time":18.29060735,"remaining_time":20.87557541},
{"learn":[0.2049713779],"iteration":467,"passed_time":18.32509688,"remaining_time":20.83109304},
{"learn":[0.204866362],"iteration":468,"passed_time":18.36507945,"remaining_time":20.79287247},
{"learn":[0.2047150294],"iteration":469,"passed_time":18.40469377,"remaining_time":20.75422915},
{"learn":[0.2044790726],"iteration":470,"passed_time":18.4435882,"remaining_time":20.71477316},
{"learn":[0.2043541013],"iteration":471,"passed_time":18.48132908,"remaining_time":20.67402914},
{"learn":[0.2042293421],"iteration":472,"passed_time":18.51683018,"remaining_time":20.63080234},
{"learn":[0.2041202761],"iteration":473,"passed_time":18.56154497,"remaining_time":20.59783261},
{"learn":[0.2039304057],"iteration":474,"passed_time":18.59823229,"remaining_time":20.55594095},
{"learn":[0.2038348918],"iteration":475,"passed_time":18.63333663,"remaining_time":20.51232855},
{"learn":[0.2036494404],"iteration":476,"passed_time":18.67381954,"remaining_time":20.47464909},
{"learn":[0.2034439199],"iteration":477,"passed_time":18.70943052,"remaining_time":20.43163751},
{"learn":[0.203172647],"iteration":478,"passed_time":18.75246999,"remaining_time":20.39673667},
{"learn":[0.2030558609],"iteration":479,"passed_time":18.78990637,"remaining_time":20.35573191},
{"learn":[0.202934416],"iteration":480,"passed_time":18.82459698,"remaining_time":20.31177927},
{"learn":[0.2028203769],"iteration":481,"passed_time":18.8589308,"remaining_time":20.26748164},
{"learn":[0.2026839633],"iteration":482,"passed_time":18.90198892,"remaining_time":20.23256371},
{"learn":[0.2024706548],"iteration":483,"passed_time":18.93921364,"remaining_time":20.19139305},
{"learn":[0.2023404122],"iteration":484,"passed_time":18.97610626,"remaining_time":20.14988603},
{"learn":[0.202178768],"iteration":485,"passed_time":19.02408716,"remaining_time":20.1201251},
{"learn":[0.2020652851],"iteration":486,"passed_time":19.05928735,"remaining_time":20.0768263},
{"learn":[0.2018843995],"iteration":487,"passed_time":19.09590518,"remaining_time":20.03504805},
{"learn":[0.2017770615],"iteration":488,"passed_time":19.1336957,"remaining_time":19.99451637},
{"learn":[0.2015855802],"iteration":489,"passed_time":19.1673623,"remaining_time":19.94970362},
{"learn":[0.2014078466],"iteration":490,"passed_time":19.2036447,"remaining_time":19.90764797},
{"learn":[0.2012724939],"iteration":491,"passed_time":19.24921893,"remaining_time":19.87520979},
{"learn":[0.2011641442],"iteration":492,"passed_time":19.29186217,"remaining_time":19.8397041},
{"learn":[0.2009894718],"iteration":493,"passed_time":19.32902334,"remaining_time":19.79855428},
{"learn":[0.2008836815],"iteration":494,"passed_time":19.36853087,"remaining_time":19.75981432},
{"learn":[0.2004914986],"iteration":495,"passed_time":19.41648587,"remaining_time":19.729655},
{"learn":[0.200394298],"iteration":496,"passed_time":19.45053187,"remaining_time":19.68534714},
{"learn":[0.2002555543],"iteration":497,"passed_time":19.4891625,"remaining_time":19.64570196},
{"learn":[0.2001566518],"iteration":498,"passed_time":19.52280716,"remaining_time":19.60105488},
{"learn":[0.2000742188],"iteration":499,"passed_time":19.55741988,"remaining_time":19.55741988},
{"learn":[0.2000050713],"iteration":500,"passed_time":19.59367767,"remaining_time":19.51545939},
{"learn":[0.1998692621],"iteration":501,"passed_time":19.62954932,"remaining_time":19.47313857},
{"learn":[0.1997420306],"iteration":502,"passed_time":19.66230815,"remaining_time":19.42776769},
{"learn":[0.1995850397],"iteration":503,"passed_time":19.69782439,"remaining_time":19.38516051},
{"learn":[0.1994787089],"iteration":504,"passed_time":19.7323128,"remaining_time":19.34157393},
{"learn":[0.199246541],"iteration":505,"passed_time":19.77916318,"remaining_time":19.31009212},
{"learn":[0.1991635114],"iteration":506,"passed_time":19.81824529,"remaining_time":19.27099592},
{"learn":[0.199058224],"iteration":507,"passed_time":19.86323308,"remaining_time":19.23761944},
{"learn":[0.1989520881],"iteration":508,"passed_time":19.90367854,"remaining_time":19.19981565},
{"learn":[0.1988313155],"iteration":509,"passed_time":19.93951499,"remaining_time":19.15757323},
{"learn":[0.1987106939],"iteration":510,"passed_time":19.97681864,"remaining_time":19.11675992},
{"learn":[0.1985501034],"iteration":511,"passed_time":20.01696913,"remaining_time":19.0786737},
{"learn":[0.1983683164],"iteration":512,"passed_time":20.07066283,"remaining_time":19.05343625},
{"learn":[0.1982197804],"iteration":513,"passed_time":20.11006844,"remaining_time":19.01457833},
{"learn":[0.1980635115],"iteration":514,"passed_time":20.14731429,"remaining_time":18.97368434},
{"learn":[0.1978712847],"iteration":515,"passed_time":20.18829693,"remaining_time":18.93630953},
{"learn":[0.1977864583],"iteration":516,"passed_time":20.22386942,"remaining_time":18.8938664},
{"learn":[0.1976500246],"iteration":517,"passed_time":20.2763689,"remaining_time":18.86720041},
{"learn":[0.1975395079],"iteration":518,"passed_time":20.31227596,"remaining_time":18.8250573},
{"learn":[0.1974228663],"iteration":519,"passed_time":20.3482128,"remaining_time":18.78296566},
{"learn":[0.1973252211],"iteration":520,"passed_time":20.38978669,"remaining_time":18.74608028},
{"learn":[0.1972265575],"iteration":521,"passed_time":20.42529018,"remaining_time":18.70361821},
{"learn":[0.1971340025],"iteration":522,"passed_time":20.45857675,"remaining_time":18.65916082},
{"learn":[0.1970271986],"iteration":523,"passed_time":20.49769033,"remaining_time":18.62003931},
{"learn":[0.1968883143],"iteration":524,"passed_time":20.54027003,"remaining_time":18.58405384},
{"learn":[0.1967295559],"iteration":525,"passed_time":20.58151495,"remaining_time":18.54684046},
{"learn":[0.1965963024],"iteration":526,"passed_time":20.62077499,"remaining_time":18.50783031},
{"learn":[0.1964742594],"iteration":527,"passed_time":20.65980591,"remaining_time":18.46861437},
{"learn":[0.1963385323],"iteration":528,"passed_time":20.70313214,"remaining_time":18.43322352},
{"learn":[0.1961903997],"iteration":529,"passed_time":20.7388939,"remaining_time":18.39109459},
{"learn":[0.1960650412],"iteration":530,"passed_time":20.77326849,"remaining_time":18.34776445},
{"learn":[0.1959544544],"iteration":531,"passed_time":20.80978302,"remaining_time":18.30635048},
{"learn":[0.1958705829],"iteration":532,"passed_time":20.84461335,"remaining_time":18.26347924},
{"learn":[0.1957326019],"iteration":533,"passed_time":20.89024868,"remaining_time":18.2300672},
{"learn":[0.195594102],"iteration":534,"passed_time":20.92575126,"remaining_time":18.18780249},
{"learn":[0.1955049846],"iteration":535,"passed_time":20.95844182,"remaining_time":18.14312874},
{"learn":[0.1953675138],"iteration":536,"passed_time":20.99734745,"remaining_time":18.10385823},
{"learn":[0.1952431643],"iteration":537,"passed_time":21.03457652,"remaining_time":18.06314935},
{"learn":[0.1951417194],"iteration":538,"passed_time":21.06863732,"remaining_time":18.01974361},
{"learn":[0.1948560652],"iteration":539,"passed_time":21.11422845,"remaining_time":17.9861946},
{"learn":[0.1947400501],"iteration":540,"passed_time":21.14977526,"remaining_time":17.9440792},
{"learn":[0.1946414155],"iteration":541,"passed_time":21.18898643,"remaining_time":17.90508448},
{"learn":[0.1945270511],"iteration":542,"passed_time":21.22336589,"remaining_time":17.86202249},
{"learn":[0.1943962032],"iteration":543,"passed_time":21.26199745,"remaining_time":17.82255668},
{"learn":[0.1942914233],"iteration":544,"passed_time":21.30536476,"remaining_time":17.78704764},
{"learn":[0.1941613425],"iteration":545,"passed_time":21.34779081,"remaining_time":17.75072716},
{"learn":[0.1939830559],"iteration":546,"passed_time":21.38620499,"remaining_time":17.7110619},
{"learn":[0.1938223353],"iteration":547,"passed_time":21.4178005,"remaining_time":17.66577705},
{"learn":[0.1936708578],"iteration":548,"passed_time":21.44967104,"remaining_time":17.62076801},
{"learn":[0.1935166697],"iteration":549,"passed_time":21.48528446,"remaining_time":17.57886911},
{"learn":[0.1934324832],"iteration":550,"passed_time":21.52959594,"remaining_time":17.5440809},
{"learn":[0.1932854818],"iteration":551,"passed_time":21.56112627,"remaining_time":17.49888509},
{"learn":[0.1932247728],"iteration":552,"passed_time":21.59782927,"remaining_time":17.45791986},
{"learn":[0.193120838],"iteration":553,"passed_time":21.62943937,"remaining_time":17.41286996},
{"learn":[0.1930019188],"iteration":554,"passed_time":21.66226988,"remaining_time":17.36884702},
{"learn":[0.192879406],"iteration":555,"passed_time":21.69880057,"remaining_time":17.32781916},
{"learn":[0.192751043],"iteration":556,"passed_time":21.73023978,"remaining_time":17.28275803},
{"learn":[0.1926958253],"iteration":557,"passed_time":21.76140909,"remaining_time":17.23753193},
{"learn":[0.1926184252],"iteration":558,"passed_time":21.7966049,"remaining_time":17.19553267},
{"learn":[0.1925351275],"iteration":559,"passed_time":21.8280838,"remaining_time":17.15063727},
{"learn":[0.1923512355],"iteration":560,"passed_time":21.86074425,"remaining_time":17.10671431},
{"learn":[0.1922085001],"iteration":561,"passed_time":21.89873193,"remaining_time":17.06698325},
{"learn":[0.1920470629],"iteration":562,"passed_time":21.94482008,"remaining_time":17.03354596},
{"learn":[0.1919077118],"iteration":563,"passed_time":21.97721062,"remaining_time":16.98947488},
{"learn":[0.1917533207],"iteration":564,"passed_time":22.01097254,"remaining_time":16.94650098},
{"learn":[0.191570193],"iteration":565,"passed_time":22.04388168,"remaining_time":16.90290574},
{"learn":[0.1914153929],"iteration":566,"passed_time":22.07878274,"remaining_time":16.86086936},
{"learn":[0.1913114509],"iteration":567,"passed_time":22.11302861,"remaining_time":16.81835979},
{"learn":[0.1912164615],"iteration":568,"passed_time":22.14470425,"remaining_time":16.7739324},
{"learn":[0.1911380271],"iteration":569,"passed_time":22.18299121,"remaining_time":16.73453723},
{"learn":[0.1909658003],"iteration":570,"passed_time":22.21607363,"remaining_time":16.6912357},
{"learn":[0.1908777448],"iteration":571,"passed_time":22.24684436,"remaining_time":16.64624018},
{"learn":[0.1907240424],"iteration":572,"passed_time":22.27990569,"remaining_time":16.60300127},
{"learn":[0.1904544233],"iteration":573,"passed_time":22.32857018,"remaining_time":16.57137787},
{"learn":[0.1903256645],"iteration":574,"passed_time":22.35998184,"remaining_time":16.5269431},
{"learn":[0.1901519679],"iteration":575,"passed_time":22.39762499,"remaining_time":16.48714062},
{"learn":[0.1900727944],"iteration":576,"passed_time":22.42872079,"remaining_time":16.44254575},
{"learn":[0.1899380628],"iteration":577,"passed_time":22.46230738,"remaining_time":16.39981611},
{"learn":[0.1898343588],"iteration":578,"passed_time":22.49813496,"remaining_time":16.35874753},
{"learn":[0.189748421],"iteration":579,"passed_time":22.53006056,"remaining_time":16.31487144},
{"learn":[0.1896634355],"iteration":580,"passed_time":22.56253351,"remaining_time":16.27143122},
{"learn":[0.1895807617],"iteration":581,"passed_time":22.59525183,"remaining_time":16.22820492},
{"learn":[0.1894611192],"iteration":582,"passed_time":22.6276693,"remaining_time":16.18479948},
{"learn":[0.1893445654],"iteration":583,"passed_time":22.66032958,"remaining_time":16.14160463},
{"learn":[0.1892651863],"iteration":584,"passed_time":22.69247524,"remaining_time":16.09808073},
{"learn":[0.1891395967],"iteration":585,"passed_time":22.7246263,"remaining_time":16.05459947},
{"learn":[0.1890702795],"iteration":586,"passed_time":22.77173755,"remaining_time":16.02168247},
{"learn":[0.1889508357],"iteration":587,"passed_time":22.8019377,"remaining_time":15.97686791},
{"learn":[0.1888204415],"iteration":588,"passed_time":22.83180218,"remaining_time":15.93186875},
{"learn":[0.1886721846],"iteration":589,"passed_time":22.87624675,"remaining_time":15.89705283},
{"learn":[0.1886233005],"iteration":590,"passed_time":22.90712872,"remaining_time":15.85281836},
{"learn":[0.1884556969],"iteration":591,"passed_time":22.93874163,"remaining_time":15.80913275},
{"learn":[0.1883360638],"iteration":592,"passed_time":22.97723828,"remaining_time":15.77021244},
{"learn":[0.1881922155],"iteration":593,"passed_time":23.01068998,"remaining_time":15.72784534},
{"learn":[0.1881057156],"iteration":594,"passed_time":23.04242354,"remaining_time":15.68433871},
{"learn":[0.1879705966],"iteration":595,"passed_time":23.07626967,"remaining_time":15.6423036},
{"learn":[0.187639276],"iteration":596,"passed_time":23.10834847,"remaining_time":15.5991029},
{"learn":[0.1875401558],"iteration":597,"passed_time":23.14004151,"remaining_time":15.55568008},
{"learn":[0.187426262],"iteration":598,"passed_time":23.17545044,"remaining_time":15.51478402},
{"learn":[0.1873340358],"iteration":599,"passed_time":23.21225126,"remaining_time":15.47483417},
{"learn":[0.1872492005],"iteration":600,"passed_time":23.25152857,"remaining_time":15.43653894},
{"learn":[0.1871513246],"iteration":601,"passed_time":23.28671931,"remaining_time":15.39553868},
{"learn":[0.187033888],"iteration":602,"passed_time":23.31870411,"remaining_time":15.35244698},
{"learn":[0.1869382042],"iteration":603,"passed_time":23.34924622,"remaining_time":15.3084462},
{"learn":[0.1868009509],"iteration":604,"passed_time":23.38715032,"remaining_time":15.26929649},
{"learn":[0.1866912314],"iteration":605,"passed_time":23.4201337,"remaining_time":15.22695161},
{"learn":[0.1865956988],"iteration":606,"passed_time":23.45308867,"remaining_time":15.18461919},
{"learn":[0.1864632166],"iteration":607,"passed_time":23.48568576,"remaining_time":15.14208687},
{"learn":[0.1863126042],"iteration":608,"passed_time":23.51799302,"remaining_time":15.0994011},
{"learn":[0.1861796062],"iteration":609,"passed_time":23.54809962,"remaining_time":15.05534238},
{"learn":[0.186067845],"iteration":610,"passed_time":23.58092881,"remaining_time":15.0130627},
{"learn":[0.1859829299],"iteration":611,"passed_time":23.61050036,"remaining_time":14.96874859},
{"learn":[0.1858721579],"iteration":612,"passed_time":23.65281084,"remaining_time":14.93252495},
{"learn":[0.1857808551],"iteration":613,"passed_time":23.68631509,"remaining_time":14.89074532},
{"learn":[0.1856778176],"iteration":614,"passed_time":23.71748119,"remaining_time":14.84752887},
{"learn":[0.1854914481],"iteration":615,"passed_time":23.74780996,"remaining_time":14.80382958},
{"learn":[0.1853646598],"iteration":616,"passed_time":23.78291017,"remaining_time":14.76313548},
{"learn":[0.1852651457],"iteration":617,"passed_time":23.81561358,"remaining_time":14.72097797},
{"learn":[0.1851450147],"iteration":618,"passed_time":23.85500754,"remaining_time":14.6829691},
{"learn":[0.1850588134],"iteration":619,"passed_time":23.88812048,"remaining_time":14.6411061},
{"learn":[0.184965921],"iteration":620,"passed_time":23.91838837,"remaining_time":14.59753493},
{"learn":[0.1847862634],"iteration":621,"passed_time":23.9483593,"remaining_time":14.55382607},
{"learn":[0.1847072583],"iteration":622,"passed_time":23.98146489,"remaining_time":14.51205821},
{"learn":[0.1845578126],"iteration":623,"passed_time":24.01873789,"remaining_time":14.47282924},
{"learn":[0.1844243179],"iteration":624,"passed_time":24.06088541,"remaining_time":14.43653125},
{"learn":[0.1843343573],"iteration":625,"passed_time":24.09308738,"remaining_time":14.39427265},
{"learn":[0.1842583163],"iteration":626,"passed_time":24.12222443,"remaining_time":14.35022282},
{"learn":[0.1841609117],"iteration":627,"passed_time":24.15975934,"remaining_time":14.31119503},
{"learn":[0.1840074045],"iteration":628,"passed_time":24.19272972,"remaining_time":14.26947969},
{"learn":[0.1838621693],"iteration":629,"passed_time":24.22232916,"remaining_time":14.22581236},
{"learn":[0.1837759372],"iteration":630,"passed_time":24.25764131,"remaining_time":14.18553034},
{"learn":[0.1837213378],"iteration":631,"passed_time":24.28942684,"remaining_time":14.14321057},
{"learn":[0.1836279293],"iteration":632,"passed_time":24.32139708,"remaining_time":14.10103117},
{"learn":[0.1835266841],"iteration":633,"passed_time":24.35502629,"remaining_time":14.05984168},
{"learn":[0.1834323314],"iteration":634,"passed_time":24.38686343,"remaining_time":14.01764591},
{"learn":[0.1833620895],"iteration":635,"passed_time":24.42592048,"remaining_time":13.97961486},
{"learn":[0.1832581911],"iteration":636,"passed_time":24.46394606,"remaining_time":13.94099281},
{"learn":[0.183185063],"iteration":637,"passed_time":24.49441824,"remaining_time":13.89808684},
{"learn":[0.1830837218],"iteration":638,"passed_time":24.52571589,"remaining_time":13.85568613},
{"learn":[0.1828948905],"iteration":639,"passed_time":24.57680159,"remaining_time":13.8244509},
{"learn":[0.182808344],"iteration":640,"passed_time":24.60806206,"remaining_time":13.78205036},
{"learn":[0.1827011952],"iteration":641,"passed_time":24.63862965,"remaining_time":13.73929815},
{"learn":[0.1826102814],"iteration":642,"passed_time":24.67995921,"remaining_time":13.702559},
{"learn":[0.1825518947],"iteration":643,"passed_time":24.75803953,"remaining_time":13.68612123},
{"learn":[0.1824425368],"iteration":644,"passed_time":24.8760452,"remaining_time":13.69146674},
{"learn":[0.1823586087],"iteration":645,"passed_time":24.91849324,"remaining_time":13.65502571},
{"learn":[0.1822604422],"iteration":646,"passed_time":24.95313734,"remaining_time":13.61430831},
{"learn":[0.1821597352],"iteration":647,"passed_time":24.98514712,"remaining_time":13.57217868},
{"learn":[0.1820439718],"iteration":648,"passed_time":25.01496692,"remaining_time":13.52889582},
{"learn":[0.1819568411],"iteration":649,"passed_time":25.05248062,"remaining_time":13.48979726},
{"learn":[0.1818391042],"iteration":650,"passed_time":25.08485196,"remaining_time":13.44794675},
{"learn":[0.1817659681],"iteration":651,"passed_time":25.11984692,"remaining_time":13.40752565},
{"learn":[0.1816917658],"iteration":652,"passed_time":25.15217515,"remaining_time":13.3657041},
{"learn":[0.1815713601],"iteration":653,"passed_time":25.18296092,"remaining_time":13.32309553},
{"learn":[0.1814252978],"iteration":654,"passed_time":25.21738391,"remaining_time":13.28243885},
{"learn":[0.1813558243],"iteration":655,"passed_time":25.24714458,"remaining_time":13.23935631},
{"learn":[0.1812839553],"iteration":656,"passed_time":25.29631366,"remaining_time":13.20644686},
{"learn":[0.1811570653],"iteration":657,"passed_time":25.32901724,"remaining_time":13.16492993},
{"learn":[0.1810789527],"iteration":658,"passed_time":25.36029425,"remaining_time":13.12270158},
{"learn":[0.181008629],"iteration":659,"passed_time":25.39069223,"remaining_time":13.08005357},
{"learn":[0.1809201131],"iteration":660,"passed_time":25.42745358,"remaining_time":13.04070615},
{"learn":[0.1807912877],"iteration":661,"passed_time":25.45911374,"remaining_time":12.998762},
{"learn":[0.1806861077],"iteration":662,"passed_time":25.50225744,"remaining_time":12.96268591},
{"learn":[0.180610851],"iteration":663,"passed_time":25.53214514,"remaining_time":12.91988067},
{"learn":[0.1804989976],"iteration":664,"passed_time":25.56526462,"remaining_time":12.87874233},
{"learn":[0.1802482443],"iteration":665,"passed_time":25.60004899,"remaining_time":12.83846301},
{"learn":[0.180161103],"iteration":666,"passed_time":25.63475955,"remaining_time":12.79816332},
{"learn":[0.1800340641],"iteration":667,"passed_time":25.66959294,"remaining_time":12.7579414},
{"learn":[0.1799092984],"iteration":668,"passed_time":25.70677542,"remaining_time":12.71889785},
{"learn":[0.1798455851],"iteration":669,"passed_time":25.74125369,"remaining_time":12.67852794},
{"learn":[0.1797236332],"iteration":670,"passed_time":25.77380414,"remaining_time":12.63723035},
{"learn":[0.1796039674],"iteration":671,"passed_time":25.810843,"remaining_time":12.59814956},
{"learn":[0.1794556764],"iteration":672,"passed_time":25.84962354,"remaining_time":12.55992109},
{"learn":[0.1793462816],"iteration":673,"passed_time":25.8828257,"remaining_time":12.51899285},
{"learn":[0.1792593969],"iteration":674,"passed_time":25.91144662,"remaining_time":12.4758817},
{"learn":[0.1790814522],"iteration":675,"passed_time":25.94371786,"remaining_time":12.434563},
{"learn":[0.1790078442],"iteration":676,"passed_time":25.97617788,"remaining_time":12.39336109},
{"learn":[0.1789234241],"iteration":677,"passed_time":26.01752086,"remaining_time":12.35640371},
{"learn":[0.178845245],"iteration":678,"passed_time":26.07688222,"remaining_time":12.32795168},
{"learn":[0.1787815104],"iteration":679,"passed_time":26.11992804,"remaining_time":12.29173084},
{"learn":[0.1787091947],"iteration":680,"passed_time":26.16224236,"remaining_time":12.2551473},
{"learn":[0.1786025976],"iteration":681,"passed_time":26.19556058,"remaining_time":12.2143523},
{"learn":[0.1785162074],"iteration":682,"passed_time":26.23925144,"remaining_time":12.17839342},
{"learn":[0.1783558393],"iteration":683,"passed_time":26.27177387,"remaining_time":12.13725226},
{"learn":[0.1782375142],"iteration":684,"passed_time":26.30188095,"remaining_time":12.09502555},
{"learn":[0.1781442458],"iteration":685,"passed_time":26.33660773,"remaining_time":12.05494873},
{"learn":[0.1780525465],"iteration":686,"passed_time":26.36802942,"remaining_time":12.01338167},
{"learn":[0.1779831074],"iteration":687,"passed_time":26.40467536,"remaining_time":11.97421325},
{"learn":[0.1778661204],"iteration":688,"passed_time":26.43546853,"remaining_time":11.93241033},
{"learn":[0.1777589071],"iteration":689,"passed_time":26.46349761,"remaining_time":11.88939747},
{"learn":[0.1776549724],"iteration":690,"passed_time":26.49929582,"remaining_time":11.84990218},
{"learn":[0.1775849763],"iteration":691,"passed_time":26.53256174,"remaining_time":11.80929049},
{"learn":[0.1774272197],"iteration":692,"passed_time":26.57645095,"remaining_time":11.77340612},
{"learn":[0.1773508469],"iteration":693,"passed_time":26.60935474,"remaining_time":11.73265497},
{"learn":[0.1772849656],"iteration":694,"passed_time":26.64180712,"remaining_time":11.6917283},
{"learn":[0.1771879891],"iteration":695,"passed_time":26.68491919,"remaining_time":11.65548194},
{"learn":[0.1771163304],"iteration":696,"passed_time":26.71782122,"remaining_time":11.61477737},
{"learn":[0.1770501315],"iteration":697,"passed_time":26.75019393,"remaining_time":11.57386614},
{"learn":[0.1769863445],"iteration":698,"passed_time":26.78504695,"remaining_time":11.5340474},
{"learn":[0.176857423],"iteration":699,"passed_time":26.82059633,"remaining_time":11.49454128},
{"learn":[0.1767567609],"iteration":700,"passed_time":26.85232577,"remaining_time":11.45341713},
{"learn":[0.1766502045],"iteration":701,"passed_time":26.88805583,"remaining_time":11.414018},
{"learn":[0.1765695715],"iteration":702,"passed_time":26.92046939,"remaining_time":11.37322818},
{"learn":[0.1764459589],"iteration":703,"passed_time":26.95214388,"remaining_time":11.3321514},
{"learn":[0.1763386547],"iteration":704,"passed_time":26.98757321,"remaining_time":11.29267248},
{"learn":[0.1762589824],"iteration":705,"passed_time":27.03413258,"remaining_time":11.25783991},
{"learn":[0.1761296811],"iteration":706,"passed_time":27.07185085,"remaining_time":11.21931018},
{"learn":[0.1760519185],"iteration":707,"passed_time":27.10433339,"remaining_time":11.17862338},
{"learn":[0.1759792672],"iteration":708,"passed_time":27.13788659,"remaining_time":11.13839915},
{"learn":[0.1757791073],"iteration":709,"passed_time":27.17276317,"remaining_time":11.09873425},
{"learn":[0.1757165956],"iteration":710,"passed_time":27.2046685,"remaining_time":11.0578751},
{"learn":[0.1755511277],"iteration":711,"passed_time":27.23814535,"remaining_time":11.01767677},
{"learn":[0.175472714],"iteration":712,"passed_time":27.27059146,"remaining_time":10.9770824},
{"learn":[0.1753210807],"iteration":713,"passed_time":27.30480637,"remaining_time":10.93721936},
{"learn":[0.1752427341],"iteration":714,"passed_time":27.33547402,"remaining_time":10.89595818},
{"learn":[0.1751407678],"iteration":715,"passed_time":27.36765334,"remaining_time":10.85532619},
{"learn":[0.175069155],"iteration":716,"passed_time":27.40982658,"remaining_time":10.81866237},
{"learn":[0.1749973059],"iteration":717,"passed_time":27.44640193,"remaining_time":10.7797846},
{"learn":[0.1749070688],"iteration":718,"passed_time":27.47870818,"remaining_time":10.73924478},
{"learn":[0.1748325351],"iteration":719,"passed_time":27.51255016,"remaining_time":10.69932506},
{"learn":[0.174707386],"iteration":720,"passed_time":27.54599314,"remaining_time":10.6592678},
{"learn":[0.1745930709],"iteration":721,"passed_time":27.57991213,"remaining_time":10.61941215},
{"learn":[0.1745157578],"iteration":722,"passed_time":27.61555371,"remaining_time":10.58023289},
{"learn":[0.1744639571],"iteration":723,"passed_time":27.64757896,"remaining_time":10.5396848},
{"learn":[0.1743285263],"iteration":724,"passed_time":27.68203654,"remaining_time":10.50008283},
{"learn":[0.1742222926],"iteration":725,"passed_time":27.71184707,"remaining_time":10.45874118},
{"learn":[0.1741666891],"iteration":726,"passed_time":27.74268165,"remaining_time":10.41781581},
{"learn":[0.174072366],"iteration":727,"passed_time":27.77772401,"remaining_time":10.37849029},
{"learn":[0.1739634227],"iteration":728,"passed_time":27.82715988,"remaining_time":10.3445272},
{"learn":[0.1738594644],"iteration":729,"passed_time":27.85889723,"remaining_time":10.30397569},
{"learn":[0.1737594442],"iteration":730,"passed_time":27.89606224,"remaining_time":10.26544561},
{"learn":[0.1736969801],"iteration":731,"passed_time":27.92537441,"remaining_time":10.22404418},
{"learn":[0.1736152075],"iteration":732,"passed_time":27.97291772,"remaining_time":10.18931655},
{"learn":[0.173508261],"iteration":733,"passed_time":28.02620704,"remaining_time":10.15663634},
{"learn":[0.1734464171],"iteration":734,"passed_time":28.0587795,"remaining_time":10.11643071},
{"learn":[0.1733401671],"iteration":735,"passed_time":28.09730818,"remaining_time":10.07838228},
{"learn":[0.1732344111],"iteration":736,"passed_time":28.12679467,"remaining_time":10.03710583},
{"learn":[0.1731108197],"iteration":737,"passed_time":28.15784858,"remaining_time":9.996417787},
{"learn":[0.1730054513],"iteration":738,"passed_time":28.19899183,"remaining_time":9.959319173},
{"learn":[0.1729410413],"iteration":739,"passed_time":28.23931439,"remaining_time":9.921921271},
{"learn":[0.1728740349],"iteration":740,"passed_time":28.27170563,"remaining_time":9.881743262},
{"learn":[0.1727890247],"iteration":741,"passed_time":28.30387588,"remaining_time":9.841509403},
{"learn":[0.1727226684],"iteration":742,"passed_time":28.33520731,"remaining_time":9.801007103},
{"learn":[0.1726339357],"iteration":743,"passed_time":28.36756251,"remaining_time":9.760881723},
{"learn":[0.1725769071],"iteration":744,"passed_time":28.40150289,"remaining_time":9.721319779},
{"learn":[0.1725032512],"iteration":745,"passed_time":28.43270774,"remaining_time":9.680841511},
{"learn":[0.1724151996],"iteration":746,"passed_time":28.46229094,"remaining_time":9.639838832},
{"learn":[0.1723114188],"iteration":747,"passed_time":28.49728951,"remaining_time":9.60069112},
{"learn":[0.1722593942],"iteration":748,"passed_time":28.52871933,"remaining_time":9.560358547},
{"learn":[0.1721858726],"iteration":749,"passed_time":28.55735301,"remaining_time":9.519117671},
{"learn":[0.172118092],"iteration":750,"passed_time":28.59167935,"remaining_time":9.479797813},
{"learn":[0.1720508042],"iteration":751,"passed_time":28.63321493,"remaining_time":9.442868754},
{"learn":[0.1719606013],"iteration":752,"passed_time":28.66367722,"remaining_time":9.402295182},
{"learn":[0.1718961926],"iteration":753,"passed_time":28.69690292,"remaining_time":9.362650024},
{"learn":[0.171775956],"iteration":754,"passed_time":28.73040623,"remaining_time":9.323111956},
{"learn":[0.1716934864],"iteration":755,"passed_time":28.76681846,"remaining_time":9.284528708},
{"learn":[0.1716220863],"iteration":756,"passed_time":28.806041,"remaining_time":9.246853319},
{"learn":[0.1715508853],"iteration":757,"passed_time":28.8383972,"remaining_time":9.206981692},
{"learn":[0.1714226252],"iteration":758,"passed_time":28.86890669,"remaining_time":9.166543494},
{"learn":[0.1712975222],"iteration":759,"passed_time":28.90718965,"remaining_time":9.128586205},
{"learn":[0.1712222551],"iteration":760,"passed_time":28.93767399,"remaining_time":9.088178823},
{"learn":[0.1711458524],"iteration":761,"passed_time":28.9684827,"remaining_time":9.047898797},
{"learn":[0.1710342856],"iteration":762,"passed_time":29.03900695,"remaining_time":9.01997988},
{"learn":[0.1709705349],"iteration":763,"passed_time":29.07249202,"remaining_time":8.980508006},
{"learn":[0.1708620328],"iteration":764,"passed_time":29.10847331,"remaining_time":8.941818599},
{"learn":[0.1707401225],"iteration":765,"passed_time":29.14094164,"remaining_time":8.902063111},
{"learn":[0.170677515],"iteration":766,"passed_time":29.17451336,"remaining_time":8.862661817},
{"learn":[0.1706170477],"iteration":767,"passed_time":29.20864204,"remaining_time":8.82344395},
{"learn":[0.1705331346],"iteration":768,"passed_time":29.23985241,"remaining_time":8.783362689},
{"learn":[0.1704043848],"iteration":769,"passed_time":29.27062158,"remaining_time":8.743172681},
{"learn":[0.1703092712],"iteration":770,"passed_time":29.30661896,"remaining_time":8.704559976},
{"learn":[0.1702202697],"iteration":771,"passed_time":29.33809966,"remaining_time":8.664620106},
{"learn":[0.1701608468],"iteration":772,"passed_time":29.369602,"remaining_time":8.624708477},
{"learn":[0.1700730348],"iteration":773,"passed_time":29.40801088,"remaining_time":8.586835219},
{"learn":[0.1700024745],"iteration":774,"passed_time":29.45273936,"remaining_time":8.550795298},
{"learn":[0.1699322468],"iteration":775,"passed_time":29.48793238,"remaining_time":8.51198048},
{"learn":[0.1698514609],"iteration":776,"passed_time":29.52185661,"remaining_time":8.472810841},
{"learn":[0.169751663],"iteration":777,"passed_time":29.55187817,"remaining_time":8.432541073},
{"learn":[0.1696726601],"iteration":778,"passed_time":29.58996942,"remaining_time":8.394586961},
{"learn":[0.1695348218],"iteration":779,"passed_time":29.62581256,"remaining_time":8.355998414},
{"learn":[0.1694244379],"iteration":780,"passed_time":29.66497529,"remaining_time":8.318347743},
{"learn":[0.1693463642],"iteration":781,"passed_time":29.70552913,"remaining_time":8.28108101},
{"learn":[0.1692778016],"iteration":782,"passed_time":29.73751958,"remaining_time":8.241432629},
{"learn":[0.1692368832],"iteration":783,"passed_time":29.77389434,"remaining_time":8.203011705},
{"learn":[0.1691778011],"iteration":784,"passed_time":29.80822883,"remaining_time":8.164037197},
{"learn":[0.1691118092],"iteration":785,"passed_time":29.85356857,"remaining_time":8.128070833},
{"learn":[0.1690233671],"iteration":786,"passed_time":29.88970814,"remaining_time":8.08959064},
{"learn":[0.1689477189],"iteration":787,"passed_time":29.92231033,"remaining_time":8.050164709},
{"learn":[0.1688451869],"iteration":788,"passed_time":29.95394826,"remaining_time":8.010498204},
{"learn":[0.1687836073],"iteration":789,"passed_time":29.9905017,"remaining_time":7.972158681},
{"learn":[0.168717767],"iteration":790,"passed_time":30.03323991,"remaining_time":7.935457827},
{"learn":[0.1686137247],"iteration":791,"passed_time":30.06511767,"remaining_time":7.89588949},
{"learn":[0.1685368521],"iteration":792,"passed_time":30.10094985,"remaining_time":7.857372785},
{"learn":[0.168444538],"iteration":793,"passed_time":30.13218147,"remaining_time":7.817669249},
{"learn":[0.1683620122],"iteration":794,"passed_time":30.16336072,"remaining_time":7.777973518},
{"learn":[0.1682738596],"iteration":795,"passed_time":30.20052244,"remaining_time":7.739832384},
{"learn":[0.168177202],"iteration":796,"passed_time":30.24174032,"remaining_time":7.702726831},
{"learn":[0.1680747193],"iteration":797,"passed_time":30.27464707,"remaining_time":7.663507154},
{"learn":[0.1679980459],"iteration":798,"passed_time":30.30621413,"remaining_time":7.623966258},
{"learn":[0.1679073341],"iteration":799,"passed_time":30.33717029,"remaining_time":7.584292573},
{"learn":[0.1678303288],"iteration":800,"passed_time":30.37445799,"remaining_time":7.546213658},
{"learn":[0.1677402018],"iteration":801,"passed_time":30.4065432,"remaining_time":7.50685231},
{"learn":[0.1676730023],"iteration":802,"passed_time":30.43684426,"remaining_time":7.467071381},
{"learn":[0.1676082407],"iteration":803,"passed_time":30.46996221,"remaining_time":7.428000737},
{"learn":[0.1675240255],"iteration":804,"passed_time":30.50454599,"remaining_time":7.38929996},
{"learn":[0.1674481804],"iteration":805,"passed_time":30.5348216,"remaining_time":7.349572445},
{"learn":[0.1673615342],"iteration":806,"passed_time":30.56691714,"remaining_time":7.310303603},
{"learn":[0.1673125798],"iteration":807,"passed_time":30.6111164,"remaining_time":7.273928649},
{"learn":[0.1671778216],"iteration":808,"passed_time":30.65199533,"remaining_time":7.236750442},
{"learn":[0.1671058467],"iteration":809,"passed_time":30.68802491,"remaining_time":7.198425597},
{"learn":[0.1669886095],"iteration":810,"passed_time":30.71948411,"remaining_time":7.159041302},
{"learn":[0.166889619],"iteration":811,"passed_time":30.75374132,"remaining_time":7.120324345},
{"learn":[0.166817725],"iteration":812,"passed_time":30.78710717,"remaining_time":7.081413335},
{"learn":[0.1667576034],"iteration":813,"passed_time":30.82205653,"remaining_time":7.042877782},
{"learn":[0.1666670018],"iteration":814,"passed_time":30.85402794,"remaining_time":7.003675054},
{"learn":[0.1666017086],"iteration":815,"passed_time":30.88822309,"remaining_time":6.964991481},
{"learn":[0.1665484061],"iteration":816,"passed_time":30.91896946,"remaining_time":6.925546404},
{"learn":[0.1664796862],"iteration":817,"passed_time":30.94998414,"remaining_time":6.88618229},
{"learn":[0.1662683519],"iteration":818,"passed_time":30.98495366,"remaining_time":6.847712592},
{"learn":[0.1662318151],"iteration":819,"passed_time":31.01625057,"remaining_time":6.808445248},
{"learn":[0.1661048146],"iteration":820,"passed_time":31.04778744,"remaining_time":6.769249637},
{"learn":[0.1660102202],"iteration":821,"passed_time":31.10508928,"remaining_time":6.735651936},
{"learn":[0.1659320153],"iteration":822,"passed_time":31.13339241,"remaining_time":6.695759971},
{"learn":[0.1658607145],"iteration":823,"passed_time":31.16469006,"remaining_time":6.656535741},
{"learn":[0.1657684709],"iteration":824,"passed_time":31.20076814,"remaining_time":6.618344757},
{"learn":[0.1657283682],"iteration":825,"passed_time":31.23324133,"remaining_time":6.579399506},
{"learn":[0.1656603765],"iteration":826,"passed_time":31.26501225,"remaining_time":6.540322998},
{"learn":[0.1655862553],"iteration":827,"passed_time":31.29755955,"remaining_time":6.501425415},
{"learn":[0.1655191183],"iteration":828,"passed_time":31.32794032,"remaining_time":6.462096254},
{"learn":[0.1654545538],"iteration":829,"passed_time":31.3573502,"remaining_time":6.422589801},
{"learn":[0.1653556764],"iteration":830,"passed_time":31.39257869,"remaining_time":6.384290973},
{"learn":[0.1652986687],"iteration":831,"passed_time":31.42263617,"remaining_time":6.34495538},
{"learn":[0.1652052144],"iteration":832,"passed_time":31.4528962,"remaining_time":6.305682672},
{"learn":[0.1651369084],"iteration":833,"passed_time":31.5001651,"remaining_time":6.269817034},
{"learn":[0.1650572223],"iteration":834,"passed_time":31.53131011,"remaining_time":6.230737926},
{"learn":[0.1649584937],"iteration":835,"passed_time":31.56936108,"remaining_time":6.193032557},
{"learn":[0.1648967352],"iteration":836,"passed_time":31.59699627,"remaining_time":6.15329796},
{"learn":[0.1648039366],"iteration":837,"passed_time":31.63072859,"remaining_time":6.11477092},
{"learn":[0.1646759942],"iteration":838,"passed_time":31.66872457,"remaining_time":6.077073488},
{"learn":[0.1645891295],"iteration":839,"passed_time":31.69824716,"remaining_time":6.037761363},
{"learn":[0.1645100873],"iteration":840,"passed_time":31.73298973,"remaining_time":5.999459414},
{"learn":[0.1644302756],"iteration":841,"passed_time":31.76532848,"remaining_time":5.960714846},
{"learn":[0.1643590774],"iteration":842,"passed_time":31.79569718,"remaining_time":5.921618574},
{"learn":[0.1642695486],"iteration":843,"passed_time":31.84280254,"remaining_time":5.885636489},
{"learn":[0.1641496983],"iteration":844,"passed_time":31.8780668,"remaining_time":5.84745604},
{"learn":[0.1640563169],"iteration":845,"passed_time":31.9093147,"remaining_time":5.808551376},
{"learn":[0.1639968456],"iteration":846,"passed_time":31.94393933,"remaining_time":5.770274755},
{"learn":[0.163927219],"iteration":847,"passed_time":31.97995812,"remaining_time":5.732256644},
{"learn":[0.1638093163],"iteration":848,"passed_time":32.01139421,"remaining_time":5.693428181},
{"learn":[0.163702745],"iteration":849,"passed_time":32.04309036,"remaining_time":5.654663006},
{"learn":[0.1636193947],"iteration":850,"passed_time":32.07751738,"remaining_time":5.616392585},
{"learn":[0.1635299922],"iteration":851,"passed_time":32.1078992,"remaining_time":5.5774285},
{"learn":[0.1634700991],"iteration":852,"passed_time":32.13821977,"remaining_time":5.538473981},
{"learn":[0.1633190748],"iteration":853,"passed_time":32.17452873,"remaining_time":5.500563459},
{"learn":[0.1632348363],"iteration":854,"passed_time":32.20480845,"remaining_time":5.461634181},
{"learn":[0.1631798244],"iteration":855,"passed_time":32.25375762,"remaining_time":5.425865768},
{"learn":[0.1631235059],"iteration":856,"passed_time":32.28470734,"remaining_time":5.387063185},
{"learn":[0.1630509302],"iteration":857,"passed_time":32.31384726,"remaining_time":5.347979383},
{"learn":[0.1629975772],"iteration":858,"passed_time":32.35143875,"remaining_time":5.310306012},
{"learn":[0.1629319314],"iteration":859,"passed_time":32.3816311,"remaining_time":5.271428319},
{"learn":[0.1627867872],"iteration":860,"passed_time":32.41459211,"remaining_time":5.233017774},
{"learn":[0.1627214419],"iteration":861,"passed_time":32.45444654,"remaining_time":5.19572346},
{"learn":[0.1626579869],"iteration":862,"passed_time":32.48525944,"remaining_time":5.156987884},
{"learn":[0.162574153],"iteration":863,"passed_time":32.51775045,"remaining_time":5.118534793},
{"learn":[0.1623627307],"iteration":864,"passed_time":32.55321617,"remaining_time":5.080559748},
{"learn":[0.1622818181],"iteration":865,"passed_time":32.58278892,"remaining_time":5.041678654},
{"learn":[0.162202718],"iteration":866,"passed_time":32.61130718,"remaining_time":5.002657272},
{"learn":[0.1620741332],"iteration":867,"passed_time":32.64374285,"remaining_time":4.964255826},
{"learn":[0.1619676398],"iteration":868,"passed_time":32.67752893,"remaining_time":4.926071679},
{"learn":[0.1618527143],"iteration":869,"passed_time":32.72939999,"remaining_time":4.890599998},
{"learn":[0.1617786038],"iteration":870,"passed_time":32.7688703,"remaining_time":4.85325404},
{"learn":[0.1616988213],"iteration":871,"passed_time":32.79843999,"remaining_time":4.814449907},
{"learn":[0.1616262224],"iteration":872,"passed_time":32.82843799,"remaining_time":4.775729238},
{"learn":[0.1614856595],"iteration":873,"passed_time":32.86827641,"remaining_time":4.738447172},
{"learn":[0.1614080784],"iteration":874,"passed_time":32.89931141,"remaining_time":4.69990163},
{"learn":[0.1613164677],"iteration":875,"passed_time":32.93078675,"remaining_time":4.661435567},
{"learn":[0.1612199445],"iteration":876,"passed_time":32.9651895,"remaining_time":4.623396019},
{"learn":[0.1611372847],"iteration":877,"passed_time":32.99495108,"remaining_time":4.584719854},
{"learn":[0.1610426511],"iteration":878,"passed_time":33.02530021,"remaining_time":4.546144852},
{"learn":[0.1609823653],"iteration":879,"passed_time":33.06282379,"remaining_time":4.50856688},
{"learn":[0.1608858729],"iteration":880,"passed_time":33.09607263,"remaining_time":4.470411626},
{"learn":[0.160841356],"iteration":881,"passed_time":33.14534699,"remaining_time":4.434411503},
{"learn":[0.1607428892],"iteration":882,"passed_time":33.17379663,"remaining_time":4.395621977},
{"learn":[0.1606858222],"iteration":883,"passed_time":33.20512121,"remaining_time":4.3572331},
{"learn":[0.160581872],"iteration":884,"passed_time":33.23754344,"remaining_time":4.31900282},
{"learn":[0.1605050744],"iteration":885,"passed_time":33.27541811,"remaining_time":4.281487207},
{"learn":[0.1604293204],"iteration":886,"passed_time":33.30428697,"remaining_time":4.242823481},
{"learn":[0.1603425376],"iteration":887,"passed_time":33.33569861,"remaining_time":4.204502528},
{"learn":[0.1602608262],"iteration":888,"passed_time":33.36910568,"remaining_time":4.166446266},
{"learn":[0.1601995193],"iteration":889,"passed_time":33.40106548,"remaining_time":4.128221576},
{"learn":[0.1601302206],"iteration":890,"passed_time":33.43287898,"remaining_time":4.089993051},
{"learn":[0.1600715406],"iteration":891,"passed_time":33.46573537,"remaining_time":4.051905179},
{"learn":[0.160011064],"iteration":892,"passed_time":33.49555447,"remaining_time":4.013465093},
{"learn":[0.1599327846],"iteration":893,"passed_time":33.54227039,"remaining_time":3.977047719},
{"learn":[0.1598587171],"iteration":894,"passed_time":33.56936024,"remaining_time":3.938304832},
{"learn":[0.1598076899],"iteration":895,"passed_time":33.59860455,"remaining_time":3.899838029},
{"learn":[0.1596623422],"iteration":896,"passed_time":33.63237598,"remaining_time":3.861911623},
{"learn":[0.1596196878],"iteration":897,"passed_time":33.66886042,"remaining_time":3.824302631},
{"learn":[0.1595700037],"iteration":898,"passed_time":33.70783346,"remaining_time":3.786975728},
{"learn":[0.159525113],"iteration":899,"passed_time":33.73931754,"remaining_time":3.74881306},
{"learn":[0.1594607781],"iteration":900,"passed_time":33.77557726,"remaining_time":3.711189955},
{"learn":[0.1593325171],"iteration":901,"passed_time":33.80626144,"remaining_time":3.672964103},
{"learn":[0.1592556851],"iteration":902,"passed_time":33.83866632,"remaining_time":3.634939793},
{"learn":[0.1591511767],"iteration":903,"passed_time":33.87489696,"remaining_time":3.597334191},
{"learn":[0.1590979412],"iteration":904,"passed_time":33.91230637,"remaining_time":3.559855365},
{"learn":[0.1589973104],"iteration":905,"passed_time":33.94903155,"remaining_time":3.522305702},
{"learn":[0.158906928],"iteration":906,"passed_time":33.98441075,"remaining_time":3.484619846},
{"learn":[0.1588240944],"iteration":907,"passed_time":34.01770893,"remaining_time":3.446728218},
{"learn":[0.1587481468],"iteration":908,"passed_time":34.05645876,"remaining_time":3.409392461},
{"learn":[0.1586708255],"iteration":909,"passed_time":34.09032432,"remaining_time":3.371570537},
{"learn":[0.1586080108],"iteration":910,"passed_time":34.12240927,"remaining_time":3.333583343},
{"learn":[0.1585426483],"iteration":911,"passed_time":34.15519976,"remaining_time":3.29567717},
{"learn":[0.1584315756],"iteration":912,"passed_time":34.18731087,"remaining_time":3.257717465},
{"learn":[0.1583646782],"iteration":913,"passed_time":34.21542508,"remaining_time":3.219394482},
{"learn":[0.1582658113],"iteration":914,"passed_time":34.25254976,"remaining_time":3.181930852},
{"learn":[0.1581999601],"iteration":915,"passed_time":34.2841227,"remaining_time":3.14395885},
{"learn":[0.15801468],"iteration":916,"passed_time":34.32379473,"remaining_time":3.106733875},
{"learn":[0.1579268982],"iteration":917,"passed_time":34.36701703,"remaining_time":3.069820693},
{"learn":[0.1578530839],"iteration":918,"passed_time":34.39964663,"remaining_time":3.031960149},
{"learn":[0.1577918841],"iteration":919,"passed_time":34.4280328,"remaining_time":2.993741982},
{"learn":[0.157702511],"iteration":920,"passed_time":34.46843393,"remaining_time":2.956575766},
{"learn":[0.1576240622],"iteration":921,"passed_time":34.49686118,"remaining_time":2.918389558},
{"learn":[0.1575116479],"iteration":922,"passed_time":34.52807593,"remaining_time":2.880457038},
{"learn":[0.1573914924],"iteration":923,"passed_time":34.56768826,"remaining_time":2.84322977},
{"learn":[0.1572909423],"iteration":924,"passed_time":34.5990602,"remaining_time":2.805329206},
{"learn":[0.1571578808],"iteration":925,"passed_time":34.62985363,"remaining_time":2.76739651},
{"learn":[0.1571088877],"iteration":926,"passed_time":34.66867322,"remaining_time":2.730111267},
{"learn":[0.15705456],"iteration":927,"passed_time":34.70379499,"remaining_time":2.692535818},
{"learn":[0.156991898],"iteration":928,"passed_time":34.75136956,"remaining_time":2.655917372},
{"learn":[0.1569212157],"iteration":929,"passed_time":34.78259657,"remaining_time":2.618044903},
{"learn":[0.1568162797],"iteration":930,"passed_time":34.81256675,"remaining_time":2.580093562},
{"learn":[0.1567280862],"iteration":931,"passed_time":34.84886292,"remaining_time":2.5426209},
{"learn":[0.1566899592],"iteration":932,"passed_time":34.88141002,"remaining_time":2.504881534},
{"learn":[0.1566230132],"iteration":933,"passed_time":34.91397043,"remaining_time":2.467154227},
{"learn":[0.1565756254],"iteration":934,"passed_time":34.94441176,"remaining_time":2.429290657},
{"learn":[0.1565140177],"iteration":935,"passed_time":34.97422659,"remaining_time":2.391400109},
{"learn":[0.1564359209],"iteration":936,"passed_time":35.00700795,"remaining_time":2.353726255},
{"learn":[0.1563759029],"iteration":937,"passed_time":35.03889549,"remaining_time":2.316003753},
{"learn":[0.1563127085],"iteration":938,"passed_time":35.07407878,"remaining_time":2.27850778},
{"learn":[0.1562283552],"iteration":939,"passed_time":35.10811581,"remaining_time":2.240943562},
{"learn":[0.1561488225],"iteration":940,"passed_time":35.15885136,"remaining_time":2.204433826},
{"learn":[0.1560873314],"iteration":941,"passed_time":35.18885186,"remaining_time":2.166617206},
{"learn":[0.1559994188],"iteration":942,"passed_time":35.21988521,"remaining_time":2.128879594},
{"learn":[0.1559412672],"iteration":943,"passed_time":35.25483101,"remaining_time":2.09138828},
{"learn":[0.1558739607],"iteration":944,"passed_time":35.28539778,"remaining_time":2.05364749},
{"learn":[0.1558152247],"iteration":945,"passed_time":35.31734694,"remaining_time":2.016000777},
{"learn":[0.1557319879],"iteration":946,"passed_time":35.35223574,"remaining_time":1.978530617},
{"learn":[0.155639254],"iteration":947,"passed_time":35.38559963,"remaining_time":1.940982258},
{"learn":[0.1555878666],"iteration":948,"passed_time":35.41585753,"remaining_time":1.9032758},
{"learn":[0.1555426028],"iteration":949,"passed_time":35.45392074,"remaining_time":1.865995829},
{"learn":[0.1554709209],"iteration":950,"passed_time":35.48493883,"remaining_time":1.828351212},
{"learn":[0.1554077283],"iteration":951,"passed_time":35.51555842,"remaining_time":1.790700425},
{"learn":[0.1553545196],"iteration":952,"passed_time":35.54706697,"remaining_time":1.753108235},
{"learn":[0.155292126],"iteration":953,"passed_time":35.59526405,"remaining_time":1.716333487},
{"learn":[0.1551851364],"iteration":954,"passed_time":35.6276495,"remaining_time":1.678789767},
{"learn":[0.1551082518],"iteration":955,"passed_time":35.66222915,"remaining_time":1.641357827},
{"learn":[0.154998728],"iteration":956,"passed_time":35.69872477,"remaining_time":1.604017936},
{"learn":[0.1549147971],"iteration":957,"passed_time":35.730989,"remaining_time":1.566494299},
{"learn":[0.1548571682],"iteration":958,"passed_time":35.76560115,"remaining_time":1.529082009},
{"learn":[0.1547996506],"iteration":959,"passed_time":35.79555511,"remaining_time":1.491481463},
{"learn":[0.1547468949],"iteration":960,"passed_time":35.82807548,"remaining_time":1.454000982},
{"learn":[0.1546895588],"iteration":961,"passed_time":35.8633232,"remaining_time":1.416638546},
{"learn":[0.1545744674],"iteration":962,"passed_time":35.89286288,"remaining_time":1.379061191},
{"learn":[0.1545156487],"iteration":963,"passed_time":35.92552147,"remaining_time":1.341616984},
{"learn":[0.1544520591],"iteration":964,"passed_time":35.98248766,"remaining_time":1.305064319},
{"learn":[0.1543808858],"iteration":965,"passed_time":36.01183006,"remaining_time":1.267497124},
{"learn":[0.1543119195],"iteration":966,"passed_time":36.0428205,"remaining_time":1.230003182},
{"learn":[0.1542219319],"iteration":967,"passed_time":36.07567133,"remaining_time":1.192584176},
{"learn":[0.1541728699],"iteration":968,"passed_time":36.10719866,"remaining_time":1.155132258},
{"learn":[0.1540937547],"iteration":969,"passed_time":36.13742905,"remaining_time":1.117652445},
{"learn":[0.1539883113],"iteration":970,"passed_time":36.17118965,"remaining_time":1.080292997},
{"learn":[0.1539425402],"iteration":971,"passed_time":36.2012346,"remaining_time":1.042833918},
{"learn":[0.1538627937],"iteration":972,"passed_time":36.23136701,"remaining_time":1.005392507},
{"learn":[0.1537736984],"iteration":973,"passed_time":36.26831236,"remaining_time":0.9681479686},
{"learn":[0.1537419719],"iteration":974,"passed_time":36.29666366,"remaining_time":0.9306836837},
{"learn":[0.1536936185],"iteration":975,"passed_time":36.32703744,"remaining_time":0.8932878058},
{"learn":[0.153619489],"iteration":976,"passed_time":36.37511459,"remaining_time":0.856323066},
{"learn":[0.1535877553],"iteration":977,"passed_time":36.40340453,"remaining_time":0.8188904905},
{"learn":[0.1535149863],"iteration":978,"passed_time":36.43458717,"remaining_time":0.7815386421},
{"learn":[0.1534590852],"iteration":979,"passed_time":36.47042161,"remaining_time":0.7442943186},
{"learn":[0.1533875958],"iteration":980,"passed_time":36.50322064,"remaining_time":0.7069940796},
{"learn":[0.153335986],"iteration":981,"passed_time":36.53450388,"remaining_time":0.6696752238},
{"learn":[0.1532746842],"iteration":982,"passed_time":36.56986404,"remaining_time":0.6324391543},
{"learn":[0.1531942725],"iteration":983,"passed_time":36.60060905,"remaining_time":0.5951318544},
{"learn":[0.153102766],"iteration":984,"passed_time":36.63405543,"remaining_time":0.5578790167},
{"learn":[0.1529947631],"iteration":985,"passed_time":36.66973458,"remaining_time":0.5206656026},
{"learn":[0.1529264533],"iteration":986,"passed_time":36.70657838,"remaining_time":0.4834706372},
{"learn":[0.1528605722],"iteration":987,"passed_time":36.75150122,"remaining_time":0.4463745088},
{"learn":[0.1527954984],"iteration":988,"passed_time":36.78682774,"remaining_time":0.4091558191},
{"learn":[0.1527446419],"iteration":989,"passed_time":36.81860118,"remaining_time":0.3719050624},
{"learn":[0.1526537127],"iteration":990,"passed_time":36.85648554,"remaining_time":0.3347208575},
{"learn":[0.1525725953],"iteration":991,"passed_time":36.88517719,"remaining_time":0.2974611064},
{"learn":[0.1525031707],"iteration":992,"passed_time":36.91863119,"remaining_time":0.2602521836},
{"learn":[0.1524523243],"iteration":993,"passed_time":36.95565957,"remaining_time":0.2230723918},
{"learn":[0.152380884],"iteration":994,"passed_time":36.98534865,"remaining_time":0.1858560234},
{"learn":[0.1522593471],"iteration":995,"passed_time":37.01912496,"remaining_time":0.1486711846},
{"learn":[0.1520892264],"iteration":996,"passed_time":37.05802149,"remaining_time":0.1115085903},
{"learn":[0.152008457],"iteration":997,"passed_time":37.08725647,"remaining_time":0.07432315927},
{"learn":[0.1519258883],"iteration":998,"passed_time":37.120509,"remaining_time":0.03715766666},
{"learn":[0.1518159054],"iteration":999,"passed_time":37.168311,"remaining_time":0}
]}